{"action":{"identity":{"address":"N\u0000sourcecred\u0000core\u0000IDENTITY\u0000HXh5z8HDBwvUZRFmbI7Mog\u0000","aliases":[],"id":"HXh5z8HDBwvUZRFmbI7Mog","name":"mvellank","subtype":"USER"},"type":"CREATE_IDENTITY"},"ledgerTimestamp":1604621739768,"uuid":"aL3oIx3pgkA4enACKBSLKg","version":"1"}
{"action":{"alias":{"address":"N\u0000sourcecred\u0000discord\u0000MEMBER\u0000user\u000086122883520163840\u0000","description":"discord/mvellank#9180"},"identityId":"HXh5z8HDBwvUZRFmbI7Mog","type":"ADD_ALIAS"},"ledgerTimestamp":1604621739769,"uuid":"vo8bTBMdYkRBI4KLyM3fvA","version":"1"}
{"action":{"identity":{"address":"N\u0000sourcecred\u0000core\u0000IDENTITY\u000059ZzLGCpSx0y9NwzCArjPQ\u0000","aliases":[],"id":"59ZzLGCpSx0y9NwzCArjPQ","name":"lauren","subtype":"USER"},"type":"CREATE_IDENTITY"},"ledgerTimestamp":1604621739769,"uuid":"ls2AVtZog4KWw3jOdH3wVg","version":"1"}
{"action":{"alias":{"address":"N\u0000sourcecred\u0000discord\u0000MEMBER\u0000user\u0000111007386507948032\u0000","description":"discord/lauren#6518"},"identityId":"59ZzLGCpSx0y9NwzCArjPQ","type":"ADD_ALIAS"},"ledgerTimestamp":1604621739769,"uuid":"ivXuoAqeW9QSayakKIbRwQ","version":"1"}
{"action":{"identity":{"address":"N\u0000sourcecred\u0000core\u0000IDENTITY\u00008CBbn4gfVZy8MTQgKCkMiw\u0000","aliases":[],"id":"8CBbn4gfVZy8MTQgKCkMiw","name":"Dyno","subtype":"BOT"},"type":"CREATE_IDENTITY"},"ledgerTimestamp":1604621739769,"uuid":"yZKrSqphVUBtAdGar2gFkQ","version":"1"}
{"action":{"alias":{"address":"N\u0000sourcecred\u0000discord\u0000MEMBER\u0000bot\u0000155149108183695360\u0000","description":"discord/Dyno#3861"},"identityId":"8CBbn4gfVZy8MTQgKCkMiw","type":"ADD_ALIAS"},"ledgerTimestamp":1604621739769,"uuid":"kOACdZ69t8LMf0lzBV9U9g","version":"1"}
{"action":{"identity":{"address":"N\u0000sourcecred\u0000core\u0000IDENTITY\u000006LPzFrfQFLASjm6QN9GHQ\u0000","aliases":[],"id":"06LPzFrfQFLASjm6QN9GHQ","name":"Tony","subtype":"USER"},"type":"CREATE_IDENTITY"},"ledgerTimestamp":1604621739770,"uuid":"XbE7VDQORnc724oUORuJIg","version":"1"}
{"action":{"alias":{"address":"N\u0000sourcecred\u0000discord\u0000MEMBER\u0000user\u0000163457318514720768\u0000","description":"discord/Tony#5838"},"identityId":"06LPzFrfQFLASjm6QN9GHQ","type":"ADD_ALIAS"},"ledgerTimestamp":1604621739770,"uuid":"KlLAD19nYwo10aQA33kQXQ","version":"1"}
{"action":{"identity":{"address":"N\u0000sourcecred\u0000core\u0000IDENTITY\u0000DLEWiYN7eefz1pYkubsBpA\u0000","aliases":[],"id":"DLEWiYN7eefz1pYkubsBpA","name":"madcapslaugh","subtype":"USER"},"type":"CREATE_IDENTITY"},"ledgerTimestamp":1604621739770,"uuid":"6GYbs7meoNy42nWLA3oVRg","version":"1"}
{"action":{"alias":{"address":"N\u0000sourcecred\u0000discord\u0000MEMBER\u0000user\u0000183833390569619456\u0000","description":"discord/madcapslaugh#8503"},"identityId":"DLEWiYN7eefz1pYkubsBpA","type":"ADD_ALIAS"},"ledgerTimestamp":1604621739770,"uuid":"NJFPsYcaok1z0nmYoHyMNg","version":"1"}
{"action":{"identity":{"address":"N\u0000sourcecred\u0000core\u0000IDENTITY\u0000savCZZIK8kGFKQgmv20otA\u0000","aliases":[],"id":"savCZZIK8kGFKQgmv20otA","name":"trevor","subtype":"USER"},"type":"CREATE_IDENTITY"},"ledgerTimestamp":1604621739771,"uuid":"lIWH3BjB5cMW71JLCvzCrg","version":"1"}
{"action":{"alias":{"address":"N\u0000sourcecred\u0000discord\u0000MEMBER\u0000user\u0000185622689975762954\u0000","description":"discord/trevor#5528"},"identityId":"savCZZIK8kGFKQgmv20otA","type":"ADD_ALIAS"},"ledgerTimestamp":1604621739771,"uuid":"AgbHewedR4NvmpOBcQIvkA","version":"1"}
{"action":{"identity":{"address":"N\u0000sourcecred\u0000core\u0000IDENTITY\u0000uaaw6XekFAc0U146EWkMjA\u0000","aliases":[],"id":"uaaw6XekFAc0U146EWkMjA","name":"cybourgeoisie","subtype":"USER"},"type":"CREATE_IDENTITY"},"ledgerTimestamp":1604621739771,"uuid":"2MN8nQRdBDzTreWhD5JQKQ","version":"1"}
{"action":{"alias":{"address":"N\u0000sourcecred\u0000discord\u0000MEMBER\u0000user\u0000196432880988061697\u0000","description":"discord/cybourgeoisie#1187"},"identityId":"uaaw6XekFAc0U146EWkMjA","type":"ADD_ALIAS"},"ledgerTimestamp":1604621739771,"uuid":"MHlPcGdczR4IoO8hJHvaFA","version":"1"}
{"action":{"identity":{"address":"N\u0000sourcecred\u0000core\u0000IDENTITY\u0000VwJKGd6NXaen4COAjc4i6A\u0000","aliases":[],"id":"VwJKGd6NXaen4COAjc4i6A","name":"Nick---Upshot","subtype":"USER"},"type":"CREATE_IDENTITY"},"ledgerTimestamp":1604621739771,"uuid":"zNDvd0nM3gXjxEh6guD81Q","version":"1"}
{"action":{"alias":{"address":"N\u0000sourcecred\u0000discord\u0000MEMBER\u0000user\u0000199948360201797632\u0000","description":"discord/Nick | Upshot#2800"},"identityId":"VwJKGd6NXaen4COAjc4i6A","type":"ADD_ALIAS"},"ledgerTimestamp":1604621739771,"uuid":"kuX3ZuK567G0BXnH0iVl3g","version":"1"}
{"action":{"identity":{"address":"N\u0000sourcecred\u0000core\u0000IDENTITY\u0000oZHQloJLSYcPkRNXxSM81g\u0000","aliases":[],"id":"oZHQloJLSYcPkRNXxSM81g","name":"KyleSamani","subtype":"USER"},"type":"CREATE_IDENTITY"},"ledgerTimestamp":1604621739772,"uuid":"BQZaHGH1txUY7CqF6EJadQ","version":"1"}
{"action":{"alias":{"address":"N\u0000sourcecred\u0000discord\u0000MEMBER\u0000user\u0000213026434774597632\u0000","description":"discord/KyleSamani#4570"},"identityId":"oZHQloJLSYcPkRNXxSM81g","type":"ADD_ALIAS"},"ledgerTimestamp":1604621739772,"uuid":"ZeqkVZmTBaKKBJQs8rJnZA","version":"1"}
{"action":{"identity":{"address":"N\u0000sourcecred\u0000core\u0000IDENTITY\u0000JlnNvmbCRBLQT1otk55hgQ\u0000","aliases":[],"id":"JlnNvmbCRBLQT1otk55hgQ","name":"Canaan","subtype":"USER"},"type":"CREATE_IDENTITY"},"ledgerTimestamp":1604621739772,"uuid":"f1CA4ugizEnzCEXHdSws5g","version":"1"}
{"action":{"alias":{"address":"N\u0000sourcecred\u0000discord\u0000MEMBER\u0000user\u0000213172021578694661\u0000","description":"discord/Canaan#1656"},"identityId":"JlnNvmbCRBLQT1otk55hgQ","type":"ADD_ALIAS"},"ledgerTimestamp":1604621739772,"uuid":"agH3eqpQkKNw4ndSLHRyAw","version":"1"}
{"action":{"identity":{"address":"N\u0000sourcecred\u0000core\u0000IDENTITY\u0000z6HRDXteJuE7BcBgsMvueA\u0000","aliases":[],"id":"z6HRDXteJuE7BcBgsMvueA","name":"linda","subtype":"USER"},"type":"CREATE_IDENTITY"},"ledgerTimestamp":1604621739772,"uuid":"tK7iAl37Wb3vG404YB7JRw","version":"1"}
{"action":{"alias":{"address":"N\u0000sourcecred\u0000discord\u0000MEMBER\u0000user\u0000215718102170599424\u0000","description":"discord/linda#4622"},"identityId":"z6HRDXteJuE7BcBgsMvueA","type":"ADD_ALIAS"},"ledgerTimestamp":1604621739772,"uuid":"ioPk1mjGgQL5L0gGym4CkQ","version":"1"}
{"action":{"identity":{"address":"N\u0000sourcecred\u0000core\u0000IDENTITY\u0000HKXEjWVsWIwGo7CQFJ4VVQ\u0000","aliases":[],"id":"HKXEjWVsWIwGo7CQFJ4VVQ","name":"Scott---CT---Rabbit-Hole","subtype":"USER"},"type":"CREATE_IDENTITY"},"ledgerTimestamp":1604621739772,"uuid":"29lnmsXEbHdt58eZncn50w","version":"1"}
{"action":{"alias":{"address":"N\u0000sourcecred\u0000discord\u0000MEMBER\u0000user\u0000222844791744888832\u0000","description":"discord/Scott | CT | Rabbit Hole#8411"},"identityId":"HKXEjWVsWIwGo7CQFJ4VVQ","type":"ADD_ALIAS"},"ledgerTimestamp":1604621739772,"uuid":"AI4gB9cZh6ILr3yjjfJmKg","version":"1"}
{"action":{"identity":{"address":"N\u0000sourcecred\u0000core\u0000IDENTITY\u0000d38vxCxpTBTO7o9AyVQACA\u0000","aliases":[],"id":"d38vxCxpTBTO7o9AyVQACA","name":"ppostie","subtype":"USER"},"type":"CREATE_IDENTITY"},"ledgerTimestamp":1604621739773,"uuid":"70w0D2pPbQRFz2CyWRKzAw","version":"1"}
{"action":{"alias":{"address":"N\u0000sourcecred\u0000discord\u0000MEMBER\u0000user\u0000241223129291030529\u0000","description":"discord/ppostie#8061"},"identityId":"d38vxCxpTBTO7o9AyVQACA","type":"ADD_ALIAS"},"ledgerTimestamp":1604621739773,"uuid":"YpEsBrAA2rBq3aDiOwWQCA","version":"1"}
{"action":{"identity":{"address":"N\u0000sourcecred\u0000core\u0000IDENTITY\u00001sOZFKsqvLeLDgJRQ9YKGA\u0000","aliases":[],"id":"1sOZFKsqvLeLDgJRQ9YKGA","name":"GregRocco","subtype":"USER"},"type":"CREATE_IDENTITY"},"ledgerTimestamp":1604621739773,"uuid":"JETvvzfPHZoREpuzLOzARw","version":"1"}
{"action":{"alias":{"address":"N\u0000sourcecred\u0000discord\u0000MEMBER\u0000user\u0000245321382475333632\u0000","description":"discord/GregRocco#6998"},"identityId":"1sOZFKsqvLeLDgJRQ9YKGA","type":"ADD_ALIAS"},"ledgerTimestamp":1604621739773,"uuid":"85vnSP5o59rrBaBDHrxVzQ","version":"1"}
{"action":{"identity":{"address":"N\u0000sourcecred\u0000core\u0000IDENTITY\u0000bm3GnPECPdgPsWdArj062w\u0000","aliases":[],"id":"bm3GnPECPdgPsWdArj062w","name":"Marc","subtype":"USER"},"type":"CREATE_IDENTITY"},"ledgerTimestamp":1604621739773,"uuid":"16R2OmX7NpMn0fOnIec24g","version":"1"}
{"action":{"alias":{"address":"N\u0000sourcecred\u0000discord\u0000MEMBER\u0000user\u0000256479532427509761\u0000","description":"discord/Marc#6351"},"identityId":"bm3GnPECPdgPsWdArj062w","type":"ADD_ALIAS"},"ledgerTimestamp":1604621739773,"uuid":"GLl4tWCWJeKhGaNdV9kuMQ","version":"1"}
{"action":{"identity":{"address":"N\u0000sourcecred\u0000core\u0000IDENTITY\u00009SyjuRu7NbfDjvK2S3Kdmg\u0000","aliases":[],"id":"9SyjuRu7NbfDjvK2S3Kdmg","name":"Scott---Gitcoin","subtype":"USER"},"type":"CREATE_IDENTITY"},"ledgerTimestamp":1604621739773,"uuid":"RrpKCade04VEDINRdskvYw","version":"1"}
{"action":{"alias":{"address":"N\u0000sourcecred\u0000discord\u0000MEMBER\u0000user\u0000283112394618568704\u0000","description":"discord/Scott | Gitcoin#7024"},"identityId":"9SyjuRu7NbfDjvK2S3Kdmg","type":"ADD_ALIAS"},"ledgerTimestamp":1604621739773,"uuid":"wqbxAMPo1pTMBZL1xPe1ig","version":"1"}
{"action":{"identity":{"address":"N\u0000sourcecred\u0000core\u0000IDENTITY\u0000r0DfMyaoRM5aPoZzgvPlqg\u0000","aliases":[],"id":"r0DfMyaoRM5aPoZzgvPlqg","name":"Jess-Sloss---Seed-Club","subtype":"USER"},"type":"CREATE_IDENTITY"},"ledgerTimestamp":1604621739773,"uuid":"YLjI6GvTztoaqM46EAQwFw","version":"1"}
{"action":{"alias":{"address":"N\u0000sourcecred\u0000discord\u0000MEMBER\u0000user\u0000294610483208519680\u0000","description":"discord/Jess Sloss | Seed Club#6930"},"identityId":"r0DfMyaoRM5aPoZzgvPlqg","type":"ADD_ALIAS"},"ledgerTimestamp":1604621739773,"uuid":"5enxAJG4sZ91wvy3gfJlWg","version":"1"}
{"action":{"identity":{"address":"N\u0000sourcecred\u0000core\u0000IDENTITY\u000063zGWzKyoO4ap6tkZjVZgA\u0000","aliases":[],"id":"63zGWzKyoO4ap6tkZjVZgA","name":"evanmays","subtype":"USER"},"type":"CREATE_IDENTITY"},"ledgerTimestamp":1604621739773,"uuid":"x4Zz1ao9JvsrhA144lnZuA","version":"1"}
{"action":{"alias":{"address":"N\u0000sourcecred\u0000discord\u0000MEMBER\u0000user\u0000295021471997100036\u0000","description":"discord/evanmays#5466"},"identityId":"63zGWzKyoO4ap6tkZjVZgA","type":"ADD_ALIAS"},"ledgerTimestamp":1604621739773,"uuid":"a83h8Lekk6s80iW9oW33WQ","version":"1"}
{"action":{"identity":{"address":"N\u0000sourcecred\u0000core\u0000IDENTITY\u0000XZbvwZBUJxoLXEQPrvXafw\u0000","aliases":[],"id":"XZbvwZBUJxoLXEQPrvXafw","name":"coin-artist","subtype":"USER"},"type":"CREATE_IDENTITY"},"ledgerTimestamp":1604621739774,"uuid":"F5eVkEp816Ws119jYvB9Cw","version":"1"}
{"action":{"alias":{"address":"N\u0000sourcecred\u0000discord\u0000MEMBER\u0000user\u0000300769849439682573\u0000","description":"discord/coin_artist#7264"},"identityId":"XZbvwZBUJxoLXEQPrvXafw","type":"ADD_ALIAS"},"ledgerTimestamp":1604621739774,"uuid":"OBRSANbgdjQ6ImAgeJzdmw","version":"1"}
{"action":{"identity":{"address":"N\u0000sourcecred\u0000core\u0000IDENTITY\u0000bkMvzYvWt7aOVC3i67lbSA\u0000","aliases":[],"id":"bkMvzYvWt7aOVC3i67lbSA","name":"sneg55","subtype":"USER"},"type":"CREATE_IDENTITY"},"ledgerTimestamp":1604621739774,"uuid":"xUPxxfqBhjq4YYLTNjXsQg","version":"1"}
{"action":{"alias":{"address":"N\u0000sourcecred\u0000discord\u0000MEMBER\u0000user\u0000304774095739027456\u0000","description":"discord/sneg55#3520"},"identityId":"bkMvzYvWt7aOVC3i67lbSA","type":"ADD_ALIAS"},"ledgerTimestamp":1604621739774,"uuid":"QzBZXwYJXVDx6ryA9x1PUQ","version":"1"}
{"action":{"identity":{"address":"N\u0000sourcecred\u0000core\u0000IDENTITY\u00002EOc0p43rS4ZvyCKN1qlhw\u0000","aliases":[],"id":"2EOc0p43rS4ZvyCKN1qlhw","name":"Simple-Poll","subtype":"BOT"},"type":"CREATE_IDENTITY"},"ledgerTimestamp":1604621739774,"uuid":"Mj47UnOCZQGxUxZEFPilRQ","version":"1"}
{"action":{"alias":{"address":"N\u0000sourcecred\u0000discord\u0000MEMBER\u0000bot\u0000324631108731928587\u0000","description":"discord/Simple Poll#9879"},"identityId":"2EOc0p43rS4ZvyCKN1qlhw","type":"ADD_ALIAS"},"ledgerTimestamp":1604621739774,"uuid":"pWyWNCvBbr1SqAoAOa7ovg","version":"1"}
{"action":{"identity":{"address":"N\u0000sourcecred\u0000core\u0000IDENTITY\u0000VzYnqYCKdPxvkdt1xUPJVg\u0000","aliases":[],"id":"VzYnqYCKdPxvkdt1xUPJVg","name":"rqdw","subtype":"USER"},"type":"CREATE_IDENTITY"},"ledgerTimestamp":1604621739774,"uuid":"Nj5n3skeI07S6K3lUJnW5g","version":"1"}
{"action":{"alias":{"address":"N\u0000sourcecred\u0000discord\u0000MEMBER\u0000user\u0000324710260671643648\u0000","description":"discord/rqdw#4567"},"identityId":"VzYnqYCKdPxvkdt1xUPJVg","type":"ADD_ALIAS"},"ledgerTimestamp":1604621739774,"uuid":"F4EHmgZC84lnveQVplAI0w","version":"1"}
{"action":{"identity":{"address":"N\u0000sourcecred\u0000core\u0000IDENTITY\u0000LBWtq3w8n8uOb9T7zEv3SA\u0000","aliases":[],"id":"LBWtq3w8n8uOb9T7zEv3SA","name":"kaifovo","subtype":"USER"},"type":"CREATE_IDENTITY"},"ledgerTimestamp":1604621739774,"uuid":"iLw05CQgalr3SGGoQxOb3w","version":"1"}
{"action":{"alias":{"address":"N\u0000sourcecred\u0000discord\u0000MEMBER\u0000user\u0000326756290464448513\u0000","description":"discord/kaifovo#8334"},"identityId":"LBWtq3w8n8uOb9T7zEv3SA","type":"ADD_ALIAS"},"ledgerTimestamp":1604621739774,"uuid":"A1Hm3tGyIY0P3ed9n7jvFQ","version":"1"}
{"action":{"identity":{"address":"N\u0000sourcecred\u0000core\u0000IDENTITY\u0000ulYLmdb4RJ3dzOI6IbpLQg\u0000","aliases":[],"id":"ulYLmdb4RJ3dzOI6IbpLQg","name":"Magnus---AEST--UTC-10-----mlai88","subtype":"USER"},"type":"CREATE_IDENTITY"},"ledgerTimestamp":1604621739775,"uuid":"yqk1o5T0QyKkHVm2SGtK2Q","version":"1"}
{"action":{"alias":{"address":"N\u0000sourcecred\u0000discord\u0000MEMBER\u0000user\u0000337602572514754560\u0000","description":"discord/Magnus | AEST (UTC+10) | @mlai88#3558"},"identityId":"ulYLmdb4RJ3dzOI6IbpLQg","type":"ADD_ALIAS"},"ledgerTimestamp":1604621739775,"uuid":"640WRy1qnpVB90VhQ6Wayw","version":"1"}
{"action":{"identity":{"address":"N\u0000sourcecred\u0000core\u0000IDENTITY\u0000LYaCmUAKjpbyR6viwE6ZOA\u0000","aliases":[],"id":"LYaCmUAKjpbyR6viwE6ZOA","name":"gordo","subtype":"USER"},"type":"CREATE_IDENTITY"},"ledgerTimestamp":1604621739775,"uuid":"CpAJnmpolyGq9gKzvYiXWQ","version":"1"}
{"action":{"alias":{"address":"N\u0000sourcecred\u0000discord\u0000MEMBER\u0000user\u0000337615426727051264\u0000","description":"discord/gordo#2371"},"identityId":"LYaCmUAKjpbyR6viwE6ZOA","type":"ADD_ALIAS"},"ledgerTimestamp":1604621739775,"uuid":"cbM3LwuBviwI6F2xPAqBhw","version":"1"}
{"action":{"identity":{"address":"N\u0000sourcecred\u0000core\u0000IDENTITY\u0000sG1hYv3SAjwQfDSbnxD9pg\u0000","aliases":[],"id":"sG1hYv3SAjwQfDSbnxD9pg","name":"gish","subtype":"USER"},"type":"CREATE_IDENTITY"},"ledgerTimestamp":1604621739775,"uuid":"dfRedFvYCKuL99r0ogCk1g","version":"1"}
{"action":{"alias":{"address":"N\u0000sourcecred\u0000discord\u0000MEMBER\u0000user\u0000340326158900133889\u0000","description":"discord/gish#5901"},"identityId":"sG1hYv3SAjwQfDSbnxD9pg","type":"ADD_ALIAS"},"ledgerTimestamp":1604621739775,"uuid":"DWDFzmGgVvd059pNxZUncQ","version":"1"}
{"action":{"identity":{"address":"N\u0000sourcecred\u0000core\u0000IDENTITY\u0000888PAndyw7BxPHyekcXIAA\u0000","aliases":[],"id":"888PAndyw7BxPHyekcXIAA","name":"Lakshman","subtype":"USER"},"type":"CREATE_IDENTITY"},"ledgerTimestamp":1604621739775,"uuid":"HQizEkxLkjNrnL22xDKiAw","version":"1"}
{"action":{"alias":{"address":"N\u0000sourcecred\u0000discord\u0000MEMBER\u0000user\u0000345680403052625930\u0000","description":"discord/Lakshman#8509"},"identityId":"888PAndyw7BxPHyekcXIAA","type":"ADD_ALIAS"},"ledgerTimestamp":1604621739775,"uuid":"ywpE7rXj4jnnFyW5PE6kDQ","version":"1"}
{"action":{"identity":{"address":"N\u0000sourcecred\u0000core\u0000IDENTITY\u00007WemKsmGsblIpcRwxtoxmA\u0000","aliases":[],"id":"7WemKsmGsblIpcRwxtoxmA","name":"Kevin-C","subtype":"USER"},"type":"CREATE_IDENTITY"},"ledgerTimestamp":1604621739775,"uuid":"RsRNpgfmARQValEHWSJMKw","version":"1"}
{"action":{"alias":{"address":"N\u0000sourcecred\u0000discord\u0000MEMBER\u0000user\u0000354117669789892630\u0000","description":"discord/Kevin C#0001"},"identityId":"7WemKsmGsblIpcRwxtoxmA","type":"ADD_ALIAS"},"ledgerTimestamp":1604621739775,"uuid":"uVKzawNfNbsGYmlbFV5inA","version":"1"}
{"action":{"identity":{"address":"N\u0000sourcecred\u0000core\u0000IDENTITY\u0000QxKLpK7s6FAtAwvQsYGI6A\u0000","aliases":[],"id":"QxKLpK7s6FAtAwvQsYGI6A","name":"BiggiePoppins","subtype":"USER"},"type":"CREATE_IDENTITY"},"ledgerTimestamp":1604621739776,"uuid":"732E9XQ6dj4lgQA733OYlg","version":"1"}
{"action":{"alias":{"address":"N\u0000sourcecred\u0000discord\u0000MEMBER\u0000user\u0000361339374715273217\u0000","description":"discord/BiggiePoppins#3417"},"identityId":"QxKLpK7s6FAtAwvQsYGI6A","type":"ADD_ALIAS"},"ledgerTimestamp":1604621739776,"uuid":"WdOP8LN8FBjtdVfRqaIx6A","version":"1"}
{"action":{"identity":{"address":"N\u0000sourcecred\u0000core\u0000IDENTITY\u00005RKJn474E2H5nzuDSdun6Q\u0000","aliases":[],"id":"5RKJn474E2H5nzuDSdun6Q","name":"Fab-","subtype":"USER"},"type":"CREATE_IDENTITY"},"ledgerTimestamp":1604621739776,"uuid":"Joz3dN9vZrHW8HzC6XnBtQ","version":"1"}
{"action":{"alias":{"address":"N\u0000sourcecred\u0000discord\u0000MEMBER\u0000user\u0000365233211556757505\u0000","description":"discord/Fab&#xD8;#8941"},"identityId":"5RKJn474E2H5nzuDSdun6Q","type":"ADD_ALIAS"},"ledgerTimestamp":1604621739777,"uuid":"ULbGxgAvZCdet4RXFWrpSA","version":"1"}
{"action":{"identity":{"address":"N\u0000sourcecred\u0000core\u0000IDENTITY\u0000xUKkG748hbnWaY42053Nlw\u0000","aliases":[],"id":"xUKkG748hbnWaY42053Nlw","name":"Mike","subtype":"USER"},"type":"CREATE_IDENTITY"},"ledgerTimestamp":1604621739777,"uuid":"4NlO5XnNOCvmca5Ap3zSRg","version":"1"}
{"action":{"alias":{"address":"N\u0000sourcecred\u0000discord\u0000MEMBER\u0000user\u0000366922548832632833\u0000","description":"discord/Mike#2722"},"identityId":"xUKkG748hbnWaY42053Nlw","type":"ADD_ALIAS"},"ledgerTimestamp":1604621739777,"uuid":"EJqjSvNtoIoFmgPUn9YGDg","version":"1"}
{"action":{"identity":{"address":"N\u0000sourcecred\u0000core\u0000IDENTITY\u0000BK6JhmEflwAaQXo0QbzhgQ\u0000","aliases":[],"id":"BK6JhmEflwAaQXo0QbzhgQ","name":"Zapier","subtype":"BOT"},"type":"CREATE_IDENTITY"},"ledgerTimestamp":1604621739777,"uuid":"NuKlosYgz87mC4VtRKl4Kw","version":"1"}
{"action":{"alias":{"address":"N\u0000sourcecred\u0000discord\u0000MEMBER\u0000bot\u0000368105370532577280\u0000","description":"discord/Zapier#0625"},"identityId":"BK6JhmEflwAaQXo0QbzhgQ","type":"ADD_ALIAS"},"ledgerTimestamp":1604621739777,"uuid":"4lXsMgx3lbaka4N3NV7VEA","version":"1"}
{"action":{"identity":{"address":"N\u0000sourcecred\u0000core\u0000IDENTITY\u0000AiKkDckkc4SbAOD8Y11GlQ\u0000","aliases":[],"id":"AiKkDckkc4SbAOD8Y11GlQ","name":"Jimbobbins","subtype":"USER"},"type":"CREATE_IDENTITY"},"ledgerTimestamp":1604621739777,"uuid":"Kr9tpI5w4jy23epsNoZGYg","version":"1"}
{"action":{"alias":{"address":"N\u0000sourcecred\u0000discord\u0000MEMBER\u0000user\u0000368671950144274436\u0000","description":"discord/Jimbobbins#2707"},"identityId":"AiKkDckkc4SbAOD8Y11GlQ","type":"ADD_ALIAS"},"ledgerTimestamp":1604621739777,"uuid":"TJloJylld9VUN0fjecvzXQ","version":"1"}
{"action":{"identity":{"address":"N\u0000sourcecred\u0000core\u0000IDENTITY\u0000WiKmey9LcZf4mTnRf8UZIA\u0000","aliases":[],"id":"WiKmey9LcZf4mTnRf8UZIA","name":"rehash","subtype":"USER"},"type":"CREATE_IDENTITY"},"ledgerTimestamp":1604621739777,"uuid":"BawDbx5l9ooP9jQ58PxQag","version":"1"}
{"action":{"alias":{"address":"N\u0000sourcecred\u0000discord\u0000MEMBER\u0000user\u0000370612512980336651\u0000","description":"discord/rehash#8009"},"identityId":"WiKmey9LcZf4mTnRf8UZIA","type":"ADD_ALIAS"},"ledgerTimestamp":1604621739777,"uuid":"cDIxyuBIxSEz01x7QXKjKg","version":"1"}
{"action":{"identity":{"address":"N\u0000sourcecred\u0000core\u0000IDENTITY\u0000T4QjqFni8ey39VMKRm3nzA\u0000","aliases":[],"id":"T4QjqFni8ey39VMKRm3nzA","name":"AMPIRE","subtype":"USER"},"type":"CREATE_IDENTITY"},"ledgerTimestamp":1604621739777,"uuid":"tvf3uRQUzg8dbMKMOTYPog","version":"1"}
{"action":{"alias":{"address":"N\u0000sourcecred\u0000discord\u0000MEMBER\u0000user\u0000372218885161877514\u0000","description":"discord/AMPIRE#7681"},"identityId":"T4QjqFni8ey39VMKRm3nzA","type":"ADD_ALIAS"},"ledgerTimestamp":1604621739777,"uuid":"EvoW3yuO0xWCP7IZz47KRA","version":"1"}
{"action":{"identity":{"address":"N\u0000sourcecred\u0000core\u0000IDENTITY\u0000aat9jXZ7GgBgFXvMv64BJA\u0000","aliases":[],"id":"aat9jXZ7GgBgFXvMv64BJA","name":"bflynn","subtype":"USER"},"type":"CREATE_IDENTITY"},"ledgerTimestamp":1604621739778,"uuid":"XjkZNXtXgl9iBKbG4sgskQ","version":"1"}
{"action":{"alias":{"address":"N\u0000sourcecred\u0000discord\u0000MEMBER\u0000user\u0000372372643782983691\u0000","description":"discord/bflynn#4073"},"identityId":"aat9jXZ7GgBgFXvMv64BJA","type":"ADD_ALIAS"},"ledgerTimestamp":1604621739778,"uuid":"t6L5Js8nj5XEENWwfPdM6g","version":"1"}
{"action":{"identity":{"address":"N\u0000sourcecred\u0000core\u0000IDENTITY\u0000cV1n3asQPYc8kIruWQKc2w\u0000","aliases":[],"id":"cV1n3asQPYc8kIruWQKc2w","name":"dame-doubleu","subtype":"USER"},"type":"CREATE_IDENTITY"},"ledgerTimestamp":1604621739778,"uuid":"BkqG0IDkki0G5agVI78VYw","version":"1"}
{"action":{"alias":{"address":"N\u0000sourcecred\u0000discord\u0000MEMBER\u0000user\u0000374067624457535489\u0000","description":"discord/dame_doubleu#9397"},"identityId":"cV1n3asQPYc8kIruWQKc2w","type":"ADD_ALIAS"},"ledgerTimestamp":1604621739778,"uuid":"6mTXBEx9vNh5PdW43OH0Eg","version":"1"}
{"action":{"identity":{"address":"N\u0000sourcecred\u0000core\u0000IDENTITY\u0000UAsJxDpByBkBUPbdfrGuVw\u0000","aliases":[],"id":"UAsJxDpByBkBUPbdfrGuVw","name":"Carlos---CST---FF","subtype":"USER"},"type":"CREATE_IDENTITY"},"ledgerTimestamp":1604621739778,"uuid":"qIrrWfJzUqOUQGqDAgKy0g","version":"1"}
{"action":{"alias":{"address":"N\u0000sourcecred\u0000discord\u0000MEMBER\u0000user\u0000380599412683964416\u0000","description":"discord/Carlos | CST | FF#8979"},"identityId":"UAsJxDpByBkBUPbdfrGuVw","type":"ADD_ALIAS"},"ledgerTimestamp":1604621739778,"uuid":"C8Rbw4UYMY3kfkjmgx1lIg","version":"1"}
{"action":{"identity":{"address":"N\u0000sourcecred\u0000core\u0000IDENTITY\u0000fBiLe1rSXBu0H1vIqg8vjg\u0000","aliases":[],"id":"fBiLe1rSXBu0H1vIqg8vjg","name":"lawson----moneymail-baker","subtype":"USER"},"type":"CREATE_IDENTITY"},"ledgerTimestamp":1604621739778,"uuid":"YgetDQ09nKN7db02WEdeZQ","version":"1"}
{"action":{"alias":{"address":"N\u0000sourcecred\u0000discord\u0000MEMBER\u0000user\u0000383461425219239936\u0000","description":"discord/lawson &#x1F4B8; moneymail baker#7156"},"identityId":"fBiLe1rSXBu0H1vIqg8vjg","type":"ADD_ALIAS"},"ledgerTimestamp":1604621739778,"uuid":"yTncqxOInPl5tawiNdb1eA","version":"1"}
{"action":{"identity":{"address":"N\u0000sourcecred\u0000core\u0000IDENTITY\u0000Qt5Mx6HWqfrd07HoxEgDxA\u0000","aliases":[],"id":"Qt5Mx6HWqfrd07HoxEgDxA","name":"alexxxyz","subtype":"USER"},"type":"CREATE_IDENTITY"},"ledgerTimestamp":1604621739778,"uuid":"3JCNArpOvD9eIkVBuAcGug","version":"1"}
{"action":{"alias":{"address":"N\u0000sourcecred\u0000discord\u0000MEMBER\u0000user\u0000384012157114777602\u0000","description":"discord/alexxxyz#6303"},"identityId":"Qt5Mx6HWqfrd07HoxEgDxA","type":"ADD_ALIAS"},"ledgerTimestamp":1604621739779,"uuid":"MLatkCxr8BMb1FnqbGDlOw","version":"1"}
{"action":{"identity":{"address":"N\u0000sourcecred\u0000core\u0000IDENTITY\u0000l2ZMBYG67mFNNViQ1zYpdA\u0000","aliases":[],"id":"l2ZMBYG67mFNNViQ1zYpdA","name":"dre","subtype":"USER"},"type":"CREATE_IDENTITY"},"ledgerTimestamp":1604621739779,"uuid":"iBtYDJJzqf5Nd0kKmNL62A","version":"1"}
{"action":{"alias":{"address":"N\u0000sourcecred\u0000discord\u0000MEMBER\u0000user\u0000385259050226679811\u0000","description":"discord/dre#7262"},"identityId":"l2ZMBYG67mFNNViQ1zYpdA","type":"ADD_ALIAS"},"ledgerTimestamp":1604621739779,"uuid":"ilKQZ4xEllfnBAhZhVsVHg","version":"1"}
{"action":{"identity":{"address":"N\u0000sourcecred\u0000core\u0000IDENTITY\u0000KxKUpBwTZcvLVe0Wro2tZg\u0000","aliases":[],"id":"KxKUpBwTZcvLVe0Wro2tZg","name":"WhySos","subtype":"USER"},"type":"CREATE_IDENTITY"},"ledgerTimestamp":1604621739779,"uuid":"9PqIB4Hjs4IjYSxbMxONjQ","version":"1"}
{"action":{"alias":{"address":"N\u0000sourcecred\u0000discord\u0000MEMBER\u0000user\u0000385895190780575744\u0000","description":"discord/WhySos#0001"},"identityId":"KxKUpBwTZcvLVe0Wro2tZg","type":"ADD_ALIAS"},"ledgerTimestamp":1604621739779,"uuid":"2Epnz9WlyMnhJRLCWegAag","version":"1"}
{"action":{"identity":{"address":"N\u0000sourcecred\u0000core\u0000IDENTITY\u00008x0P0ZMNFeWF0CXaKTMmjA\u0000","aliases":[],"id":"8x0P0ZMNFeWF0CXaKTMmjA","name":"Alex-Masmej","subtype":"USER"},"type":"CREATE_IDENTITY"},"ledgerTimestamp":1604621739779,"uuid":"CdR43f3Gk8VUYGjYUb4YFg","version":"1"}
{"action":{"alias":{"address":"N\u0000sourcecred\u0000discord\u0000MEMBER\u0000user\u0000386587341117980673\u0000","description":"discord/Alex Masmej#4264"},"identityId":"8x0P0ZMNFeWF0CXaKTMmjA","type":"ADD_ALIAS"},"ledgerTimestamp":1604621739779,"uuid":"j2TMZZwnTZglFKWEPoVeGg","version":"1"}
{"action":{"identity":{"address":"N\u0000sourcecred\u0000core\u0000IDENTITY\u0000avTJO4dOWndywLtzVqenvQ\u0000","aliases":[],"id":"avTJO4dOWndywLtzVqenvQ","name":"Fran","subtype":"USER"},"type":"CREATE_IDENTITY"},"ledgerTimestamp":1604621739779,"uuid":"ZpXXlGLwSB4rCycQEbKfjg","version":"1"}
{"action":{"alias":{"address":"N\u0000sourcecred\u0000discord\u0000MEMBER\u0000user\u0000388117002448928783\u0000","description":"discord/Fran#1792"},"identityId":"avTJO4dOWndywLtzVqenvQ","type":"ADD_ALIAS"},"ledgerTimestamp":1604621739779,"uuid":"WKUeWx2GxnyYrdLTYYXgBQ","version":"1"}
{"action":{"identity":{"address":"N\u0000sourcecred\u0000core\u0000IDENTITY\u0000jxvonGVPx1xHA188QqVpGA\u0000","aliases":[],"id":"jxvonGVPx1xHA188QqVpGA","name":"Paone","subtype":"USER"},"type":"CREATE_IDENTITY"},"ledgerTimestamp":1604621739779,"uuid":"0mZegUn81L1kYmPEVMeehg","version":"1"}
{"action":{"alias":{"address":"N\u0000sourcecred\u0000discord\u0000MEMBER\u0000user\u0000388519887644917793\u0000","description":"discord/Paone#3339"},"identityId":"jxvonGVPx1xHA188QqVpGA","type":"ADD_ALIAS"},"ledgerTimestamp":1604621739779,"uuid":"lpMVQUNbUxqRRLdugQfp9Q","version":"1"}
{"action":{"identity":{"address":"N\u0000sourcecred\u0000core\u0000IDENTITY\u0000nKfLY4olxYxMUNxEGoI5qw\u0000","aliases":[],"id":"nKfLY4olxYxMUNxEGoI5qw","name":"UBIpromoter--","subtype":"USER"},"type":"CREATE_IDENTITY"},"ledgerTimestamp":1604621739779,"uuid":"HqmrbANnNFz2YPCBXpjlCQ","version":"1"}
{"action":{"alias":{"address":"N\u0000sourcecred\u0000discord\u0000MEMBER\u0000user\u0000391253771843403790\u0000","description":"discord/UBIpromoter&#x1F506;#4402"},"identityId":"nKfLY4olxYxMUNxEGoI5qw","type":"ADD_ALIAS"},"ledgerTimestamp":1604621739779,"uuid":"3D1zOrDmlnaj5fz90DPHPw","version":"1"}
{"action":{"identity":{"address":"N\u0000sourcecred\u0000core\u0000IDENTITY\u0000nPqt8jsAKuVZVGS3U1fKqw\u0000","aliases":[],"id":"nPqt8jsAKuVZVGS3U1fKqw","name":"friedger--","subtype":"USER"},"type":"CREATE_IDENTITY"},"ledgerTimestamp":1604621739779,"uuid":"uJsKUm8PsgUzJFG26GEngg","version":"1"}
{"action":{"alias":{"address":"N\u0000sourcecred\u0000discord\u0000MEMBER\u0000user\u0000392435662420443167\u0000","description":"discord/friedger &#x4FE;#0185"},"identityId":"nPqt8jsAKuVZVGS3U1fKqw","type":"ADD_ALIAS"},"ledgerTimestamp":1604621739779,"uuid":"ZYsg5QlzAvAmlcwPotKqbw","version":"1"}
{"action":{"identity":{"address":"N\u0000sourcecred\u0000core\u0000IDENTITY\u0000WP3x9AHNwQEQulaXMPS3RQ\u0000","aliases":[],"id":"WP3x9AHNwQEQulaXMPS3RQ","name":"alx","subtype":"USER"},"type":"CREATE_IDENTITY"},"ledgerTimestamp":1604621739780,"uuid":"eCEfLlEoWRXDLWO3BJTd1Q","version":"1"}
{"action":{"alias":{"address":"N\u0000sourcecred\u0000discord\u0000MEMBER\u0000user\u0000397654234587463680\u0000","description":"discord/alx#6406"},"identityId":"WP3x9AHNwQEQulaXMPS3RQ","type":"ADD_ALIAS"},"ledgerTimestamp":1604621739780,"uuid":"4sVRDRqW7MT38k1GvMReXA","version":"1"}
{"action":{"identity":{"address":"N\u0000sourcecred\u0000core\u0000IDENTITY\u0000FKdvZUByByMdInq8KPhlDA\u0000","aliases":[],"id":"FKdvZUByByMdInq8KPhlDA","name":"Thomas-Emmanuel","subtype":"USER"},"type":"CREATE_IDENTITY"},"ledgerTimestamp":1604621739780,"uuid":"rJWSygwNneC1RoRrQzONKA","version":"1"}
{"action":{"alias":{"address":"N\u0000sourcecred\u0000discord\u0000MEMBER\u0000user\u0000400472719138750464\u0000","description":"discord/Thomas Emmanuel#5443"},"identityId":"FKdvZUByByMdInq8KPhlDA","type":"ADD_ALIAS"},"ledgerTimestamp":1604621739780,"uuid":"kK8WgzZKQLHyqcaqTMJqjA","version":"1"}
{"action":{"identity":{"address":"N\u0000sourcecred\u0000core\u0000IDENTITY\u0000A8GgZBWVfJC1NZ6aS1ruBQ\u0000","aliases":[],"id":"A8GgZBWVfJC1NZ6aS1ruBQ","name":"Alex---Zabo","subtype":"USER"},"type":"CREATE_IDENTITY"},"ledgerTimestamp":1604621739780,"uuid":"jMPu8yJG0WKYnf54sOzVSQ","version":"1"}
{"action":{"alias":{"address":"N\u0000sourcecred\u0000discord\u0000MEMBER\u0000user\u0000401511660277465090\u0000","description":"discord/Alex | Zabo#7162"},"identityId":"A8GgZBWVfJC1NZ6aS1ruBQ","type":"ADD_ALIAS"},"ledgerTimestamp":1604621739780,"uuid":"SWksRqRtLM8jBZIo1YJR1A","version":"1"}
{"action":{"identity":{"address":"N\u0000sourcecred\u0000core\u0000IDENTITY\u00005kDxwkz1z6OAQB9xkV6aUw\u0000","aliases":[],"id":"5kDxwkz1z6OAQB9xkV6aUw","name":"cousinit","subtype":"USER"},"type":"CREATE_IDENTITY"},"ledgerTimestamp":1604621739780,"uuid":"J5Ww2fooH5s94imm03SP1A","version":"1"}
{"action":{"alias":{"address":"N\u0000sourcecred\u0000discord\u0000MEMBER\u0000user\u0000402209257912532992\u0000","description":"discord/cousinit#9038"},"identityId":"5kDxwkz1z6OAQB9xkV6aUw","type":"ADD_ALIAS"},"ledgerTimestamp":1604621739780,"uuid":"ZqYdQtjpy7GGKjSYEcyGCw","version":"1"}
{"action":{"identity":{"address":"N\u0000sourcecred\u0000core\u0000IDENTITY\u0000PonXuwX64IwSZBGBptn71A\u0000","aliases":[],"id":"PonXuwX64IwSZBGBptn71A","name":"Kaito-","subtype":"USER"},"type":"CREATE_IDENTITY"},"ledgerTimestamp":1604621739780,"uuid":"xxtmvCypFNtmDyUyCNbC0w","version":"1"}
{"action":{"alias":{"address":"N\u0000sourcecred\u0000discord\u0000MEMBER\u0000user\u0000405567809188265985\u0000","description":"discord/Kaito/#3253"},"identityId":"PonXuwX64IwSZBGBptn71A","type":"ADD_ALIAS"},"ledgerTimestamp":1604621739780,"uuid":"iP4yjKYM17JRn510oIwoEA","version":"1"}
{"action":{"identity":{"address":"N\u0000sourcecred\u0000core\u0000IDENTITY\u0000pRHrQNTOQ6TqC042ykfejg\u0000","aliases":[],"id":"pRHrQNTOQ6TqC042ykfejg","name":"Bobby-Ong","subtype":"USER"},"type":"CREATE_IDENTITY"},"ledgerTimestamp":1604621739780,"uuid":"swlM9E4qQgb7cxqM450mXQ","version":"1"}
{"action":{"alias":{"address":"N\u0000sourcecred\u0000discord\u0000MEMBER\u0000user\u0000411441465340723200\u0000","description":"discord/Bobby Ong#1087"},"identityId":"pRHrQNTOQ6TqC042ykfejg","type":"ADD_ALIAS"},"ledgerTimestamp":1604621739781,"uuid":"PUWR8romQMmVKyGCbENrMQ","version":"1"}
{"action":{"identity":{"address":"N\u0000sourcecred\u0000core\u0000IDENTITY\u0000YpFe5vELykZhbU8MypeGQA\u0000","aliases":[],"id":"YpFe5vELykZhbU8MypeGQA","name":"Gary---AI-crypto","subtype":"USER"},"type":"CREATE_IDENTITY"},"ledgerTimestamp":1604621739781,"uuid":"TdbdKY7fxZ0swszYSWN45Q","version":"1"}
{"action":{"alias":{"address":"N\u0000sourcecred\u0000discord\u0000MEMBER\u0000user\u0000420651712488144898\u0000","description":"discord/Gary | AI*crypto#3838"},"identityId":"YpFe5vELykZhbU8MypeGQA","type":"ADD_ALIAS"},"ledgerTimestamp":1604621739781,"uuid":"nHWxnSAXNRDKOLoP7mj5ng","version":"1"}
{"action":{"identity":{"address":"N\u0000sourcecred\u0000core\u0000IDENTITY\u0000lXwTdE2SrSoVM6qOPGFL2w\u0000","aliases":[],"id":"lXwTdE2SrSoVM6qOPGFL2w","name":"Daryl","subtype":"USER"},"type":"CREATE_IDENTITY"},"ledgerTimestamp":1604621739781,"uuid":"PyQZklORa1AgyRDivroHMA","version":"1"}
{"action":{"alias":{"address":"N\u0000sourcecred\u0000discord\u0000MEMBER\u0000user\u0000429082133240217600\u0000","description":"discord/Daryl#6303"},"identityId":"lXwTdE2SrSoVM6qOPGFL2w","type":"ADD_ALIAS"},"ledgerTimestamp":1604621739781,"uuid":"3yeQbXOmwJsL8np7ru75KA","version":"1"}
{"action":{"identity":{"address":"N\u0000sourcecred\u0000core\u0000IDENTITY\u0000jC5ENEkZqb9ny7k8JdAqyA\u0000","aliases":[],"id":"jC5ENEkZqb9ny7k8JdAqyA","name":"tk","subtype":"USER"},"type":"CREATE_IDENTITY"},"ledgerTimestamp":1604621739781,"uuid":"7tRNRDZbZqrDArJQem7Vqg","version":"1"}
{"action":{"alias":{"address":"N\u0000sourcecred\u0000discord\u0000MEMBER\u0000user\u0000431092175078686722\u0000","description":"discord/tk#2582"},"identityId":"jC5ENEkZqb9ny7k8JdAqyA","type":"ADD_ALIAS"},"ledgerTimestamp":1604621739781,"uuid":"p3qRJBZTNvmnRXnP6tKrtQ","version":"1"}
{"action":{"identity":{"address":"N\u0000sourcecred\u0000core\u0000IDENTITY\u00006UKCx5h92eOykBrYbjOEKg\u0000","aliases":[],"id":"6UKCx5h92eOykBrYbjOEKg","name":"James-Duncan-MST","subtype":"USER"},"type":"CREATE_IDENTITY"},"ledgerTimestamp":1604621739781,"uuid":"sRKYtJwSWDsMYoqeRyQu1w","version":"1"}
{"action":{"alias":{"address":"N\u0000sourcecred\u0000discord\u0000MEMBER\u0000user\u0000436039211335024640\u0000","description":"discord/James Duncan MST#1391"},"identityId":"6UKCx5h92eOykBrYbjOEKg","type":"ADD_ALIAS"},"ledgerTimestamp":1604621739781,"uuid":"iG6PKXkA3iRsDeLI5dZlDA","version":"1"}
{"action":{"identity":{"address":"N\u0000sourcecred\u0000core\u0000IDENTITY\u0000UdfPrrKJQwxdBoyqZdgq0w\u0000","aliases":[],"id":"UdfPrrKJQwxdBoyqZdgq0w","name":"Moore-Grams","subtype":"USER"},"type":"CREATE_IDENTITY"},"ledgerTimestamp":1604621739781,"uuid":"Yxb3cG0SlOf3equ6JmE7Xw","version":"1"}
{"action":{"alias":{"address":"N\u0000sourcecred\u0000discord\u0000MEMBER\u0000user\u0000436979679128322058\u0000","description":"discord/Moore Grams#2085"},"identityId":"UdfPrrKJQwxdBoyqZdgq0w","type":"ADD_ALIAS"},"ledgerTimestamp":1604621739781,"uuid":"A7M0UzpVP86ZqA1vn9rxjg","version":"1"}
{"action":{"identity":{"address":"N\u0000sourcecred\u0000core\u0000IDENTITY\u00000oYlxzkYu6roijJjuxSg4w\u0000","aliases":[],"id":"0oYlxzkYu6roijJjuxSg4w","name":"Regan---CoinList","subtype":"USER"},"type":"CREATE_IDENTITY"},"ledgerTimestamp":1604621739782,"uuid":"vKDF73V3L9HZgK03dVakPA","version":"1"}
{"action":{"alias":{"address":"N\u0000sourcecred\u0000discord\u0000MEMBER\u0000user\u0000440966315075960843\u0000","description":"discord/Regan | CoinList#2244"},"identityId":"0oYlxzkYu6roijJjuxSg4w","type":"ADD_ALIAS"},"ledgerTimestamp":1604621739782,"uuid":"LlvEBzW7vGpQAYUDdQPu3Q","version":"1"}
{"action":{"identity":{"address":"N\u0000sourcecred\u0000core\u0000IDENTITY\u0000dhgG412HDbKdmp0uNujUzA\u0000","aliases":[],"id":"dhgG412HDbKdmp0uNujUzA","name":"pet3rpan","subtype":"USER"},"type":"CREATE_IDENTITY"},"ledgerTimestamp":1604621739782,"uuid":"OQVLcKaL72HpqvCDp8ArGA","version":"1"}
{"action":{"alias":{"address":"N\u0000sourcecred\u0000discord\u0000MEMBER\u0000user\u0000443527705250758696\u0000","description":"discord/pet3rpan#4352"},"identityId":"dhgG412HDbKdmp0uNujUzA","type":"ADD_ALIAS"},"ledgerTimestamp":1604621739782,"uuid":"qAxp2seavWhb0xuQM1Emnw","version":"1"}
{"action":{"identity":{"address":"N\u0000sourcecred\u0000core\u0000IDENTITY\u0000UqeHeKwHJplc5u1F1EfA8A\u0000","aliases":[],"id":"UqeHeKwHJplc5u1F1EfA8A","name":"derekedws","subtype":"USER"},"type":"CREATE_IDENTITY"},"ledgerTimestamp":1604621739782,"uuid":"xYJRJnAt4iaBhQGyinVeWA","version":"1"}
{"action":{"alias":{"address":"N\u0000sourcecred\u0000discord\u0000MEMBER\u0000user\u0000452511715020636160\u0000","description":"discord/derekedws#2048"},"identityId":"UqeHeKwHJplc5u1F1EfA8A","type":"ADD_ALIAS"},"ledgerTimestamp":1604621739782,"uuid":"oHzBinN4EXDfAjRYm1uLUw","version":"1"}
{"action":{"identity":{"address":"N\u0000sourcecred\u0000core\u0000IDENTITY\u00001uRFonwUYb0xOsqseESa7w\u0000","aliases":[],"id":"1uRFonwUYb0xOsqseESa7w","name":"Marc---Eastern-Time---dfuse-io","subtype":"USER"},"type":"CREATE_IDENTITY"},"ledgerTimestamp":1604621739782,"uuid":"KA3o9wv5HMp4UBwY6L280w","version":"1"}
{"action":{"alias":{"address":"N\u0000sourcecred\u0000discord\u0000MEMBER\u0000user\u0000456556973689667605\u0000","description":"discord/Marc | Eastern Time | dfuse.io#9109"},"identityId":"1uRFonwUYb0xOsqseESa7w","type":"ADD_ALIAS"},"ledgerTimestamp":1604621739782,"uuid":"G8T3vg3ipYcwNHddoXLMLg","version":"1"}
{"action":{"identity":{"address":"N\u0000sourcecred\u0000core\u0000IDENTITY\u0000sP6unaU1zKCkK8P4Iyw2hQ\u0000","aliases":[],"id":"sP6unaU1zKCkK8P4Iyw2hQ","name":"ServerStats","subtype":"BOT"},"type":"CREATE_IDENTITY"},"ledgerTimestamp":1604621739782,"uuid":"S6dHgAJNd3S8SoWR9H6Ebw","version":"1"}
{"action":{"alias":{"address":"N\u0000sourcecred\u0000discord\u0000MEMBER\u0000bot\u0000458276816071950337\u0000","description":"discord/ServerStats#0197"},"identityId":"sP6unaU1zKCkK8P4Iyw2hQ","type":"ADD_ALIAS"},"ledgerTimestamp":1604621739782,"uuid":"rqKYwkZMZAiW0uzZrgoomw","version":"1"}
{"action":{"identity":{"address":"N\u0000sourcecred\u0000core\u0000IDENTITY\u0000fD4JzeiwVCd06hk0CdQnMw\u0000","aliases":[],"id":"fD4JzeiwVCd06hk0CdQnMw","name":"Louis-grx","subtype":"USER"},"type":"CREATE_IDENTITY"},"ledgerTimestamp":1604621739783,"uuid":"j89e5X6jgGangNmNDb9c5A","version":"1"}
{"action":{"alias":{"address":"N\u0000sourcecred\u0000discord\u0000MEMBER\u0000user\u0000460722661111234560\u0000","description":"discord/Louis grx#0756"},"identityId":"fD4JzeiwVCd06hk0CdQnMw","type":"ADD_ALIAS"},"ledgerTimestamp":1604621739783,"uuid":"9iNyGRxtDfPjvkliM2fWLg","version":"1"}
{"action":{"identity":{"address":"N\u0000sourcecred\u0000core\u0000IDENTITY\u0000cETRhWtglugCLwj2Zm1PAg\u0000","aliases":[],"id":"cETRhWtglugCLwj2Zm1PAg","name":"manner---hodled","subtype":"USER"},"type":"CREATE_IDENTITY"},"ledgerTimestamp":1604621739783,"uuid":"gwHDtv5dof9o1G3iYwVgwA","version":"1"}
{"action":{"alias":{"address":"N\u0000sourcecred\u0000discord\u0000MEMBER\u0000user\u0000467005281721778187\u0000","description":"discord/manner | hodled#9328"},"identityId":"cETRhWtglugCLwj2Zm1PAg","type":"ADD_ALIAS"},"ledgerTimestamp":1604621739783,"uuid":"RErQ394dmpHgZ2McZZG7xg","version":"1"}
{"action":{"identity":{"address":"N\u0000sourcecred\u0000core\u0000IDENTITY\u00001UyNvjVixqZyslnViy37XA\u0000","aliases":[],"id":"1UyNvjVixqZyslnViy37XA","name":"roneil","subtype":"USER"},"type":"CREATE_IDENTITY"},"ledgerTimestamp":1604621739783,"uuid":"5UwrhlncacbbSqxi7VQjQw","version":"1"}
{"action":{"alias":{"address":"N\u0000sourcecred\u0000discord\u0000MEMBER\u0000user\u0000475460021136916481\u0000","description":"discord/roneil#6546"},"identityId":"1UyNvjVixqZyslnViy37XA","type":"ADD_ALIAS"},"ledgerTimestamp":1604621739783,"uuid":"mzGwb2Fbn2c8jz1OcbSzgg","version":"1"}
{"action":{"identity":{"address":"N\u0000sourcecred\u0000core\u0000IDENTITY\u0000jypZswjEUmmcPRz05T1HQA\u0000","aliases":[],"id":"jypZswjEUmmcPRz05T1HQA","name":"aleks","subtype":"USER"},"type":"CREATE_IDENTITY"},"ledgerTimestamp":1604621739783,"uuid":"OrlbTBZxwyEkij5jxv00OQ","version":"1"}
{"action":{"alias":{"address":"N\u0000sourcecred\u0000discord\u0000MEMBER\u0000user\u0000481145588386234369\u0000","description":"discord/aleks#1015"},"identityId":"jypZswjEUmmcPRz05T1HQA","type":"ADD_ALIAS"},"ledgerTimestamp":1604621739783,"uuid":"sdcpoJTlFl8uRx72dnGRFA","version":"1"}
{"action":{"identity":{"address":"N\u0000sourcecred\u0000core\u0000IDENTITY\u0000qAOLN0lUKYOvsKKXwPNdxA\u0000","aliases":[],"id":"qAOLN0lUKYOvsKKXwPNdxA","name":"Brady","subtype":"USER"},"type":"CREATE_IDENTITY"},"ledgerTimestamp":1604621739783,"uuid":"DrTpoaEQig8IrcNEDiROrw","version":"1"}
{"action":{"alias":{"address":"N\u0000sourcecred\u0000discord\u0000MEMBER\u0000user\u0000482444270687748106\u0000","description":"discord/Brady#1710"},"identityId":"qAOLN0lUKYOvsKKXwPNdxA","type":"ADD_ALIAS"},"ledgerTimestamp":1604621739783,"uuid":"dQS09SOUP8dwLc2UXrJGwA","version":"1"}
{"action":{"identity":{"address":"N\u0000sourcecred\u0000core\u0000IDENTITY\u0000Ek3LK88JBlJF8r3BTGFmBg\u0000","aliases":[],"id":"Ek3LK88JBlJF8r3BTGFmBg","name":"pridesai","subtype":"USER"},"type":"CREATE_IDENTITY"},"ledgerTimestamp":1604621739783,"uuid":"AlLKbxkRSxzx02EvKmomLQ","version":"1"}
{"action":{"alias":{"address":"N\u0000sourcecred\u0000discord\u0000MEMBER\u0000user\u0000492157636993613824\u0000","description":"discord/pridesai#8445"},"identityId":"Ek3LK88JBlJF8r3BTGFmBg","type":"ADD_ALIAS"},"ledgerTimestamp":1604621739784,"uuid":"uxrUXL6G23ol5QVZAjBO8A","version":"1"}
{"action":{"identity":{"address":"N\u0000sourcecred\u0000core\u0000IDENTITY\u000047YXZT9F5mPVmGvGBgoGWQ\u0000","aliases":[],"id":"47YXZT9F5mPVmGvGBgoGWQ","name":"naymyokk7","subtype":"USER"},"type":"CREATE_IDENTITY"},"ledgerTimestamp":1604621739784,"uuid":"dt9GPhXwzCosX854qM3nEA","version":"1"}
{"action":{"alias":{"address":"N\u0000sourcecred\u0000discord\u0000MEMBER\u0000user\u0000493635280767549440\u0000","description":"discord/naymyokk7#3371"},"identityId":"47YXZT9F5mPVmGvGBgoGWQ","type":"ADD_ALIAS"},"ledgerTimestamp":1604621739784,"uuid":"evOm0NTQPmAoMhnA6NDrCw","version":"1"}
{"action":{"identity":{"address":"N\u0000sourcecred\u0000core\u0000IDENTITY\u0000PmD6nG6G4nzNO494t9BhkQ\u0000","aliases":[],"id":"PmD6nG6G4nzNO494t9BhkQ","name":"todd-x-y--circa-","subtype":"USER"},"type":"CREATE_IDENTITY"},"ledgerTimestamp":1604621739786,"uuid":"Zo7qAc1HbwHwJzLY5ygcRA","version":"1"}
{"action":{"alias":{"address":"N\u0000sourcecred\u0000discord\u0000MEMBER\u0000user\u0000507347056533438475\u0000","description":"discord/todd.x.y (circa)#9686"},"identityId":"PmD6nG6G4nzNO494t9BhkQ","type":"ADD_ALIAS"},"ledgerTimestamp":1604621739786,"uuid":"0230ivKwLEgsVh7Mx3RlXA","version":"1"}
{"action":{"identity":{"address":"N\u0000sourcecred\u0000core\u0000IDENTITY\u0000l79F3lzAgEbU23Saio7Yzw\u0000","aliases":[],"id":"l79F3lzAgEbU23Saio7Yzw","name":"steveklebanoff","subtype":"USER"},"type":"CREATE_IDENTITY"},"ledgerTimestamp":1604621739786,"uuid":"nC35Pesd2E1HoQ3KyNR42A","version":"1"}
{"action":{"alias":{"address":"N\u0000sourcecred\u0000discord\u0000MEMBER\u0000user\u0000510136624760487953\u0000","description":"discord/steveklebanoff#8012"},"identityId":"l79F3lzAgEbU23Saio7Yzw","type":"ADD_ALIAS"},"ledgerTimestamp":1604621739786,"uuid":"1KrvmioIMfqUXAP96SKLRw","version":"1"}
{"action":{"identity":{"address":"N\u0000sourcecred\u0000core\u0000IDENTITY\u0000k9nrJDONzvKb3EnJ4Jt3Ug\u0000","aliases":[],"id":"k9nrJDONzvKb3EnJ4Jt3Ug","name":"Alex-Conway---CEST----alxcnwy","subtype":"USER"},"type":"CREATE_IDENTITY"},"ledgerTimestamp":1604621739786,"uuid":"0ECysdMVh95fZSMPrxDi0A","version":"1"}
{"action":{"alias":{"address":"N\u0000sourcecred\u0000discord\u0000MEMBER\u0000user\u0000519075961891979265\u0000","description":"discord/Alex Conway | CEST | @alxcnwy#3235"},"identityId":"k9nrJDONzvKb3EnJ4Jt3Ug","type":"ADD_ALIAS"},"ledgerTimestamp":1604621739786,"uuid":"uGWF7ePANuODz6U7WrLEjw","version":"1"}
{"action":{"identity":{"address":"N\u0000sourcecred\u0000core\u0000IDENTITY\u0000z1zKnd9j5Tlqt1FaDz3U0w\u0000","aliases":[],"id":"z1zKnd9j5Tlqt1FaDz3U0w","name":"jc","subtype":"USER"},"type":"CREATE_IDENTITY"},"ledgerTimestamp":1604621739786,"uuid":"qaDxG2pOaXVJcjJEfarQqw","version":"1"}
{"action":{"alias":{"address":"N\u0000sourcecred\u0000discord\u0000MEMBER\u0000user\u0000527027407228502037\u0000","description":"discord/jc#6763"},"identityId":"z1zKnd9j5Tlqt1FaDz3U0w","type":"ADD_ALIAS"},"ledgerTimestamp":1604621739786,"uuid":"c5V6wjgsYf47aMGIyDlTlw","version":"1"}
{"action":{"identity":{"address":"N\u0000sourcecred\u0000core\u0000IDENTITY\u0000vZQJ9E00wkXYdks4UyZCkQ\u0000","aliases":[],"id":"vZQJ9E00wkXYdks4UyZCkQ","name":"jackg","subtype":"USER"},"type":"CREATE_IDENTITY"},"ledgerTimestamp":1604621739786,"uuid":"so9BK2rsnpS9ac189xPgnA","version":"1"}
{"action":{"alias":{"address":"N\u0000sourcecred\u0000discord\u0000MEMBER\u0000user\u0000527351241093677068\u0000","description":"discord/jackg#4498"},"identityId":"vZQJ9E00wkXYdks4UyZCkQ","type":"ADD_ALIAS"},"ledgerTimestamp":1604621739786,"uuid":"70Vi3oUrDawW1rGTYG08wQ","version":"1"}
{"action":{"identity":{"address":"N\u0000sourcecred\u0000core\u0000IDENTITY\u0000oSQrfz7Z1ipBcmlPoudDJA\u0000","aliases":[],"id":"oSQrfz7Z1ipBcmlPoudDJA","name":"RichardK","subtype":"USER"},"type":"CREATE_IDENTITY"},"ledgerTimestamp":1604621739786,"uuid":"7Nbwdy3s4wRK0najRNFwmg","version":"1"}
{"action":{"alias":{"address":"N\u0000sourcecred\u0000discord\u0000MEMBER\u0000user\u0000527702219492032513\u0000","description":"discord/RichardK#6756"},"identityId":"oSQrfz7Z1ipBcmlPoudDJA","type":"ADD_ALIAS"},"ledgerTimestamp":1604621739786,"uuid":"q1Pn47H20FMCOmPYKhZOsg","version":"1"}
{"action":{"identity":{"address":"N\u0000sourcecred\u0000core\u0000IDENTITY\u000075u4guKoQ2uyugVs0bTlkw\u0000","aliases":[],"id":"75u4guKoQ2uyugVs0bTlkw","name":"Louis---CEST----albiverse","subtype":"USER"},"type":"CREATE_IDENTITY"},"ledgerTimestamp":1604621739787,"uuid":"lgT3wYYBxDWj2Gdw1t6h5w","version":"1"}
{"action":{"alias":{"address":"N\u0000sourcecred\u0000discord\u0000MEMBER\u0000user\u0000535024024200413195\u0000","description":"discord/Louis | CEST | @albiverse#6722"},"identityId":"75u4guKoQ2uyugVs0bTlkw","type":"ADD_ALIAS"},"ledgerTimestamp":1604621739787,"uuid":"Zk4j0V6Lg50cJmkrBvECYw","version":"1"}
{"action":{"identity":{"address":"N\u0000sourcecred\u0000core\u0000IDENTITY\u00001bhJ1s03PnBFapzz9cARpQ\u0000","aliases":[],"id":"1bhJ1s03PnBFapzz9cARpQ","name":"cyanobacteria","subtype":"USER"},"type":"CREATE_IDENTITY"},"ledgerTimestamp":1604621739787,"uuid":"XDPJhMRCzT8VNJdGEOIlWA","version":"1"}
{"action":{"alias":{"address":"N\u0000sourcecred\u0000discord\u0000MEMBER\u0000user\u0000541800276257144837\u0000","description":"discord/cyanobacteria#2109"},"identityId":"1bhJ1s03PnBFapzz9cARpQ","type":"ADD_ALIAS"},"ledgerTimestamp":1604621739787,"uuid":"LQeN8rXpACgI72PSPYAdZQ","version":"1"}
{"action":{"identity":{"address":"N\u0000sourcecred\u0000core\u0000IDENTITY\u0000UpJBivWFBNrh69mPQknorw\u0000","aliases":[],"id":"UpJBivWFBNrh69mPQknorw","name":"alexsingh","subtype":"USER"},"type":"CREATE_IDENTITY"},"ledgerTimestamp":1604621739787,"uuid":"a0HxNB61Uv1qKlgilXty4Q","version":"1"}
{"action":{"alias":{"address":"N\u0000sourcecred\u0000discord\u0000MEMBER\u0000user\u0000542095529644130315\u0000","description":"discord/alexsingh#2370"},"identityId":"UpJBivWFBNrh69mPQknorw","type":"ADD_ALIAS"},"ledgerTimestamp":1604621739787,"uuid":"kIjNQt5U08pWjNR7yl0TaQ","version":"1"}
{"action":{"identity":{"address":"N\u0000sourcecred\u0000core\u0000IDENTITY\u00008K0efxhvayYkZZabvop7WQ\u0000","aliases":[],"id":"8K0efxhvayYkZZabvop7WQ","name":"Ben-v2","subtype":"USER"},"type":"CREATE_IDENTITY"},"ledgerTimestamp":1604621739787,"uuid":"pveAGwUpKETlpN07YCXDXg","version":"1"}
{"action":{"alias":{"address":"N\u0000sourcecred\u0000discord\u0000MEMBER\u0000user\u0000548299579964260352\u0000","description":"discord/Ben v2#3613"},"identityId":"8K0efxhvayYkZZabvop7WQ","type":"ADD_ALIAS"},"ledgerTimestamp":1604621739787,"uuid":"rVmRSBwLmmAU6InYpkEweQ","version":"1"}
{"action":{"identity":{"address":"N\u0000sourcecred\u0000core\u0000IDENTITY\u0000fxtGnwSLhbPJgmMnXuxKSQ\u0000","aliases":[],"id":"fxtGnwSLhbPJgmMnXuxKSQ","name":"robino","subtype":"USER"},"type":"CREATE_IDENTITY"},"ledgerTimestamp":1604621739787,"uuid":"n4ocnF1kfJpvJjoI63Qxrg","version":"1"}
{"action":{"alias":{"address":"N\u0000sourcecred\u0000discord\u0000MEMBER\u0000user\u0000548960524918980610\u0000","description":"discord/robino#7008"},"identityId":"fxtGnwSLhbPJgmMnXuxKSQ","type":"ADD_ALIAS"},"ledgerTimestamp":1604621739787,"uuid":"Z6YeEKRIgovQnUEXHnRUlQ","version":"1"}
{"action":{"identity":{"address":"N\u0000sourcecred\u0000core\u0000IDENTITY\u0000cwM7hoAmtkAeQyGT13IGPQ\u0000","aliases":[],"id":"cwM7hoAmtkAeQyGT13IGPQ","name":"anil---delphi","subtype":"USER"},"type":"CREATE_IDENTITY"},"ledgerTimestamp":1604621739787,"uuid":"Yv2qyHnQVAi0GmPqnw46zg","version":"1"}
{"action":{"alias":{"address":"N\u0000sourcecred\u0000discord\u0000MEMBER\u0000user\u0000556241179545436161\u0000","description":"discord/anil | delphi#9574"},"identityId":"cwM7hoAmtkAeQyGT13IGPQ","type":"ADD_ALIAS"},"ledgerTimestamp":1604621739788,"uuid":"au01kPyahlEg1dRPFnG2SA","version":"1"}
{"action":{"identity":{"address":"N\u0000sourcecred\u0000core\u0000IDENTITY\u00005WkTvA45V2gb9nBWMGKsNQ\u0000","aliases":[],"id":"5WkTvA45V2gb9nBWMGKsNQ","name":"coopahtroopa","subtype":"USER"},"type":"CREATE_IDENTITY"},"ledgerTimestamp":1604621739788,"uuid":"Do660g33gWaCa9RaKtGtBQ","version":"1"}
{"action":{"alias":{"address":"N\u0000sourcecred\u0000discord\u0000MEMBER\u0000user\u0000560581405050929153\u0000","description":"discord/coopahtroopa#9799"},"identityId":"5WkTvA45V2gb9nBWMGKsNQ","type":"ADD_ALIAS"},"ledgerTimestamp":1604621739788,"uuid":"DkQz2yQT39PMnWF7LyEF8A","version":"1"}
{"action":{"identity":{"address":"N\u0000sourcecred\u0000core\u0000IDENTITY\u0000Oy2w3H3fQ9f7PBAHy3cAbw\u0000","aliases":[],"id":"Oy2w3H3fQ9f7PBAHy3cAbw","name":"matthew-cent","subtype":"USER"},"type":"CREATE_IDENTITY"},"ledgerTimestamp":1604621739788,"uuid":"iewzgH9FpwRn2lH4E1Yeww","version":"1"}
{"action":{"alias":{"address":"N\u0000sourcecred\u0000discord\u0000MEMBER\u0000user\u0000561067521571029001\u0000","description":"discord/matthew_cent#6585"},"identityId":"Oy2w3H3fQ9f7PBAHy3cAbw","type":"ADD_ALIAS"},"ledgerTimestamp":1604621739788,"uuid":"gkDRC1rvFQN2gDH18M4ExQ","version":"1"}
{"action":{"identity":{"address":"N\u0000sourcecred\u0000core\u0000IDENTITY\u0000Y9a1PlhGhxS7ulPr9Kojiw\u0000","aliases":[],"id":"Y9a1PlhGhxS7ulPr9Kojiw","name":"awrigh01","subtype":"USER"},"type":"CREATE_IDENTITY"},"ledgerTimestamp":1604621739788,"uuid":"NiRSxpkiewwGqgG8H958MA","version":"1"}
{"action":{"alias":{"address":"N\u0000sourcecred\u0000discord\u0000MEMBER\u0000user\u0000561663588650188820\u0000","description":"discord/awrigh01#7196"},"identityId":"Y9a1PlhGhxS7ulPr9Kojiw","type":"ADD_ALIAS"},"ledgerTimestamp":1604621739788,"uuid":"O5mTY6HmkWxqiPYt7tbRzA","version":"1"}
{"action":{"identity":{"address":"N\u0000sourcecred\u0000core\u0000IDENTITY\u0000dI5mlVVB4k67vP2v52IOfw\u0000","aliases":[],"id":"dI5mlVVB4k67vP2v52IOfw","name":"TheLizards","subtype":"USER"},"type":"CREATE_IDENTITY"},"ledgerTimestamp":1604621739789,"uuid":"nOwT85EWZu5Sr7JWRUromA","version":"1"}
{"action":{"alias":{"address":"N\u0000sourcecred\u0000discord\u0000MEMBER\u0000user\u0000574291645634183170\u0000","description":"discord/TheLizards#1271"},"identityId":"dI5mlVVB4k67vP2v52IOfw","type":"ADD_ALIAS"},"ledgerTimestamp":1604621739789,"uuid":"hRdRMJUW7jIw76vAgVMDBw","version":"1"}
{"action":{"identity":{"address":"N\u0000sourcecred\u0000core\u0000IDENTITY\u0000p2N5w3og05Pl8358fo8zyQ\u0000","aliases":[],"id":"p2N5w3og05Pl8358fo8zyQ","name":"juifcrypto","subtype":"USER"},"type":"CREATE_IDENTITY"},"ledgerTimestamp":1604621739789,"uuid":"JGwGGdGB8CAF5cBzMYk7DQ","version":"1"}
{"action":{"alias":{"address":"N\u0000sourcecred\u0000discord\u0000MEMBER\u0000user\u0000576444649590489110\u0000","description":"discord/juifcrypto#4314"},"identityId":"p2N5w3og05Pl8358fo8zyQ","type":"ADD_ALIAS"},"ledgerTimestamp":1604621739789,"uuid":"AjanYlp9YOuEI47o0Y0N1g","version":"1"}
{"action":{"identity":{"address":"N\u0000sourcecred\u0000core\u0000IDENTITY\u0000gQY3kly4zGMIwL8sXwagGQ\u0000","aliases":[],"id":"gQY3kly4zGMIwL8sXwagGQ","name":"josephit","subtype":"USER"},"type":"CREATE_IDENTITY"},"ledgerTimestamp":1604621739789,"uuid":"v63skwz8xrNURBlMF9rWng","version":"1"}
{"action":{"alias":{"address":"N\u0000sourcecred\u0000discord\u0000MEMBER\u0000user\u0000586179020786499604\u0000","description":"discord/josephit#2845"},"identityId":"gQY3kly4zGMIwL8sXwagGQ","type":"ADD_ALIAS"},"ledgerTimestamp":1604621739789,"uuid":"U2oBcRCxbXvYaIm6zIpoyA","version":"1"}
{"action":{"identity":{"address":"N\u0000sourcecred\u0000core\u0000IDENTITY\u0000MmtNN5cekwYwMZgbpgGx7g\u0000","aliases":[],"id":"MmtNN5cekwYwMZgbpgGx7g","name":"sam---et---outpost","subtype":"USER"},"type":"CREATE_IDENTITY"},"ledgerTimestamp":1604621739789,"uuid":"pGxpOyLYREoQwmz8jYZ8tg","version":"1"}
{"action":{"alias":{"address":"N\u0000sourcecred\u0000discord\u0000MEMBER\u0000user\u0000590669804684312592\u0000","description":"discord/sam | et | outpost#6567"},"identityId":"MmtNN5cekwYwMZgbpgGx7g","type":"ADD_ALIAS"},"ledgerTimestamp":1604621739789,"uuid":"2pOr73nJJl4RpEu84db1ZA","version":"1"}
{"action":{"identity":{"address":"N\u0000sourcecred\u0000core\u0000IDENTITY\u0000FVebBSdwaCgSe55LTguA0w\u0000","aliases":[],"id":"FVebBSdwaCgSe55LTguA0w","name":"simondlr","subtype":"USER"},"type":"CREATE_IDENTITY"},"ledgerTimestamp":1604621739789,"uuid":"m5DqXJxh1444p6Zd52Gbyg","version":"1"}
{"action":{"alias":{"address":"N\u0000sourcecred\u0000discord\u0000MEMBER\u0000user\u0000592383914346020864\u0000","description":"discord/simondlr#8472"},"identityId":"FVebBSdwaCgSe55LTguA0w","type":"ADD_ALIAS"},"ledgerTimestamp":1604621739789,"uuid":"xpC5GOIAGOcG20mKGb7AAA","version":"1"}
{"action":{"identity":{"address":"N\u0000sourcecred\u0000core\u0000IDENTITY\u0000atRpzm88IKaJBR5ukPyMcQ\u0000","aliases":[],"id":"atRpzm88IKaJBR5ukPyMcQ","name":"bradley---Roll","subtype":"USER"},"type":"CREATE_IDENTITY"},"ledgerTimestamp":1604621739789,"uuid":"brp7KMmFmzanvRXb6GIxcQ","version":"1"}
{"action":{"alias":{"address":"N\u0000sourcecred\u0000discord\u0000MEMBER\u0000user\u0000605846719942361118\u0000","description":"discord/bradley | Roll#4924"},"identityId":"atRpzm88IKaJBR5ukPyMcQ","type":"ADD_ALIAS"},"ledgerTimestamp":1604621739789,"uuid":"YR6mG3L3zyXPCQI1vyOg0A","version":"1"}
{"action":{"identity":{"address":"N\u0000sourcecred\u0000core\u0000IDENTITY\u0000EXLSD6d8rS5TEVWBNysKuQ\u0000","aliases":[],"id":"EXLSD6d8rS5TEVWBNysKuQ","name":"ben-oxmo--CET-","subtype":"USER"},"type":"CREATE_IDENTITY"},"ledgerTimestamp":1604621739789,"uuid":"jSQ8ZLKzVPu8Owt643DEBQ","version":"1"}
{"action":{"alias":{"address":"N\u0000sourcecred\u0000discord\u0000MEMBER\u0000user\u0000606105191690797056\u0000","description":"discord/ben.oxmo (CET)#1365"},"identityId":"EXLSD6d8rS5TEVWBNysKuQ","type":"ADD_ALIAS"},"ledgerTimestamp":1604621739789,"uuid":"phKtG9LX54IwKXwIqSdY8A","version":"1"}
{"action":{"identity":{"address":"N\u0000sourcecred\u0000core\u0000IDENTITY\u0000TAiOw04evzedFM4UKP1zZQ\u0000","aliases":[],"id":"TAiOw04evzedFM4UKP1zZQ","name":"Ian-Lapham","subtype":"USER"},"type":"CREATE_IDENTITY"},"ledgerTimestamp":1604621739789,"uuid":"11Wk0H6kZzByGGqNpCEHmQ","version":"1"}
{"action":{"alias":{"address":"N\u0000sourcecred\u0000discord\u0000MEMBER\u0000user\u0000607965271759519747\u0000","description":"discord/Ian Lapham#0307"},"identityId":"TAiOw04evzedFM4UKP1zZQ","type":"ADD_ALIAS"},"ledgerTimestamp":1604621739790,"uuid":"2wQgoefVnHgmaQHdwNfOOQ","version":"1"}
{"action":{"identity":{"address":"N\u0000sourcecred\u0000core\u0000IDENTITY\u0000KMT69pLZhB79TOAPrbiJsw\u0000","aliases":[],"id":"KMT69pLZhB79TOAPrbiJsw","name":"tip-cc","subtype":"BOT"},"type":"CREATE_IDENTITY"},"ledgerTimestamp":1604621739790,"uuid":"g5sLKDbbwm7jEXV48id0SA","version":"1"}
{"action":{"alias":{"address":"N\u0000sourcecred\u0000discord\u0000MEMBER\u0000bot\u0000617037497574359050\u0000","description":"discord/tip.cc#7731"},"identityId":"KMT69pLZhB79TOAPrbiJsw","type":"ADD_ALIAS"},"ledgerTimestamp":1604621739790,"uuid":"moz4edqcq0J6fdie2Fp1Ow","version":"1"}
{"action":{"identity":{"address":"N\u0000sourcecred\u0000core\u0000IDENTITY\u0000ZxBYgNn5DkVPllawpHK9xw\u0000","aliases":[],"id":"ZxBYgNn5DkVPllawpHK9xw","name":"reuben","subtype":"USER"},"type":"CREATE_IDENTITY"},"ledgerTimestamp":1604621739790,"uuid":"x8QulsgxhoDfv7olKwZdSQ","version":"1"}
{"action":{"alias":{"address":"N\u0000sourcecred\u0000discord\u0000MEMBER\u0000user\u0000644332380458319938\u0000","description":"discord/reuben#9335"},"identityId":"ZxBYgNn5DkVPllawpHK9xw","type":"ADD_ALIAS"},"ledgerTimestamp":1604621739790,"uuid":"EhVwxNoX1J0BhZoBv1nLYQ","version":"1"}
{"action":{"identity":{"address":"N\u0000sourcecred\u0000core\u0000IDENTITY\u0000IWk8xlney633rogQj2Bf8Q\u0000","aliases":[],"id":"IWk8xlney633rogQj2Bf8Q","name":"Brendon","subtype":"USER"},"type":"CREATE_IDENTITY"},"ledgerTimestamp":1604621739790,"uuid":"howag9HwmdWYkRna1mXb9g","version":"1"}
{"action":{"alias":{"address":"N\u0000sourcecred\u0000discord\u0000MEMBER\u0000user\u0000665368477971906563\u0000","description":"discord/Brendon#0022"},"identityId":"IWk8xlney633rogQj2Bf8Q","type":"ADD_ALIAS"},"ledgerTimestamp":1604621739790,"uuid":"ESxYdf9uGsOVULNMGemdtw","version":"1"}
{"action":{"identity":{"address":"N\u0000sourcecred\u0000core\u0000IDENTITY\u0000M25pWBboz7xP0uBEbfeeDA\u0000","aliases":[],"id":"M25pWBboz7xP0uBEbfeeDA","name":"Rocco","subtype":"USER"},"type":"CREATE_IDENTITY"},"ledgerTimestamp":1604621739790,"uuid":"2zHQ3G6XPF8HMWvQexmMiA","version":"1"}
{"action":{"alias":{"address":"N\u0000sourcecred\u0000discord\u0000MEMBER\u0000user\u0000676878077455892501\u0000","description":"discord/Rocco#5828"},"identityId":"M25pWBboz7xP0uBEbfeeDA","type":"ADD_ALIAS"},"ledgerTimestamp":1604621739790,"uuid":"B4Q2szEzS1MbJXPQUBxaeQ","version":"1"}
{"action":{"identity":{"address":"N\u0000sourcecred\u0000core\u0000IDENTITY\u0000Sr9Du8eVJj3QV0qRJspnRA\u0000","aliases":[],"id":"Sr9Du8eVJj3QV0qRJspnRA","name":"Shreyas-Hariharan","subtype":"USER"},"type":"CREATE_IDENTITY"},"ledgerTimestamp":1604621739790,"uuid":"bla0w9Y4weRZYCmtbGQB3Q","version":"1"}
{"action":{"alias":{"address":"N\u0000sourcecred\u0000discord\u0000MEMBER\u0000user\u0000678665960349106187\u0000","description":"discord/Shreyas Hariharan#2656"},"identityId":"Sr9Du8eVJj3QV0qRJspnRA","type":"ADD_ALIAS"},"ledgerTimestamp":1604621739790,"uuid":"63dibKnX8xx4pL6RDwW4oQ","version":"1"}
{"action":{"identity":{"address":"N\u0000sourcecred\u0000core\u0000IDENTITY\u0000QKSNPy4Wgc1m0mkKpJiBiw\u0000","aliases":[],"id":"QKSNPy4Wgc1m0mkKpJiBiw","name":"Chase-Chapman---Decentology","subtype":"USER"},"type":"CREATE_IDENTITY"},"ledgerTimestamp":1604621739790,"uuid":"4VUwxl4UlSK6OXRyVA0TbA","version":"1"}
{"action":{"alias":{"address":"N\u0000sourcecred\u0000discord\u0000MEMBER\u0000user\u0000688005619344605217\u0000","description":"discord/Chase Chapman | Decentology#8019"},"identityId":"QKSNPy4Wgc1m0mkKpJiBiw","type":"ADD_ALIAS"},"ledgerTimestamp":1604621739790,"uuid":"F9W2c07JKyMPKbyzH5GbrA","version":"1"}
{"action":{"identity":{"address":"N\u0000sourcecred\u0000core\u0000IDENTITY\u0000zMQ3HoIgFwMJdCn9DpBPDg\u0000","aliases":[],"id":"zMQ3HoIgFwMJdCn9DpBPDg","name":"ruby","subtype":"USER"},"type":"CREATE_IDENTITY"},"ledgerTimestamp":1604621739790,"uuid":"j3Y1NubalOuxa78dKNpRbg","version":"1"}
{"action":{"alias":{"address":"N\u0000sourcecred\u0000discord\u0000MEMBER\u0000user\u0000689200041789096005\u0000","description":"discord/ruby#5411"},"identityId":"zMQ3HoIgFwMJdCn9DpBPDg","type":"ADD_ALIAS"},"ledgerTimestamp":1604621739791,"uuid":"dFZPMO6TWWodow3oIwx0wQ","version":"1"}
{"action":{"identity":{"address":"N\u0000sourcecred\u0000core\u0000IDENTITY\u0000JDl6mbclXaGNmDPEXby9XA\u0000","aliases":[],"id":"JDl6mbclXaGNmDPEXby9XA","name":"JA","subtype":"USER"},"type":"CREATE_IDENTITY"},"ledgerTimestamp":1604621739791,"uuid":"gkxdR8l5swzvwRRVmGFVzg","version":"1"}
{"action":{"alias":{"address":"N\u0000sourcecred\u0000discord\u0000MEMBER\u0000user\u0000700155573475344455\u0000","description":"discord/JA#2759"},"identityId":"JDl6mbclXaGNmDPEXby9XA","type":"ADD_ALIAS"},"ledgerTimestamp":1604621739791,"uuid":"p8JHNdbh0lk4dakeuNLqMw","version":"1"}
{"action":{"identity":{"address":"N\u0000sourcecred\u0000core\u0000IDENTITY\u0000LppSkS70NQDeqRtb0biR4A\u0000","aliases":[],"id":"LppSkS70NQDeqRtb0biR4A","name":"Collab-Land","subtype":"BOT"},"type":"CREATE_IDENTITY"},"ledgerTimestamp":1604621739791,"uuid":"rlmOMe923A5PBcrXr6UBNA","version":"1"}
{"action":{"alias":{"address":"N\u0000sourcecred\u0000discord\u0000MEMBER\u0000bot\u0000704521096837464076\u0000","description":"discord/Collab.Land#6372"},"identityId":"LppSkS70NQDeqRtb0biR4A","type":"ADD_ALIAS"},"ledgerTimestamp":1604621739791,"uuid":"yakZIJN9XheLgJrFg40lQQ","version":"1"}
{"action":{"identity":{"address":"N\u0000sourcecred\u0000core\u0000IDENTITY\u0000ARNYzAxbm6BN9uEdMtkYew\u0000","aliases":[],"id":"ARNYzAxbm6BN9uEdMtkYew","name":"Yudai","subtype":"USER"},"type":"CREATE_IDENTITY"},"ledgerTimestamp":1604621739791,"uuid":"uDlUJZ56mIWlEwAw0FqHRw","version":"1"}
{"action":{"alias":{"address":"N\u0000sourcecred\u0000discord\u0000MEMBER\u0000user\u0000707021562980859915\u0000","description":"discord/Yudai#3699"},"identityId":"ARNYzAxbm6BN9uEdMtkYew","type":"ADD_ALIAS"},"ledgerTimestamp":1604621739791,"uuid":"y2RiNaZXSxesmESNwRF71A","version":"1"}
{"action":{"identity":{"address":"N\u0000sourcecred\u0000core\u0000IDENTITY\u0000PSwTOCy0pGjoKyCdFApmtw\u0000","aliases":[],"id":"PSwTOCy0pGjoKyCdFApmtw","name":"Joon---London----joonian","subtype":"USER"},"type":"CREATE_IDENTITY"},"ledgerTimestamp":1604621739791,"uuid":"X8FJ0NWFek6YQYKY24J0eQ","version":"1"}
{"action":{"alias":{"address":"N\u0000sourcecred\u0000discord\u0000MEMBER\u0000user\u0000708047626926555238\u0000","description":"discord/Joon | London | @joonian#1382"},"identityId":"PSwTOCy0pGjoKyCdFApmtw","type":"ADD_ALIAS"},"ledgerTimestamp":1604621739791,"uuid":"XQvleMOsMGhlYy9EXCZqvQ","version":"1"}
{"action":{"identity":{"address":"N\u0000sourcecred\u0000core\u0000IDENTITY\u0000ywMpZOQX8wjkiQE8u1dkqQ\u0000","aliases":[],"id":"ywMpZOQX8wjkiQE8u1dkqQ","name":"alexxxyz-discord","subtype":"USER"},"type":"CREATE_IDENTITY"},"ledgerTimestamp":1604621739791,"uuid":"BSzxerckFVOzn9iZsbF1sw","version":"1"}
{"action":{"alias":{"address":"N\u0000sourcecred\u0000discord\u0000MEMBER\u0000user\u0000710856581612437574\u0000","description":"discord/alexxxyz#7457"},"identityId":"ywMpZOQX8wjkiQE8u1dkqQ","type":"ADD_ALIAS"},"ledgerTimestamp":1604621739791,"uuid":"qJmWu2daQT5m1XEkai6IaA","version":"1"}
{"action":{"identity":{"address":"N\u0000sourcecred\u0000core\u0000IDENTITY\u00006ysytjPD8IONNoG82Y2AOQ\u0000","aliases":[],"id":"6ysytjPD8IONNoG82Y2AOQ","name":"nish","subtype":"USER"},"type":"CREATE_IDENTITY"},"ledgerTimestamp":1604621739791,"uuid":"IW33KZnDcoSQp7Eiy4v8iw","version":"1"}
{"action":{"alias":{"address":"N\u0000sourcecred\u0000discord\u0000MEMBER\u0000user\u0000711540045533675570\u0000","description":"discord/nish#8373"},"identityId":"6ysytjPD8IONNoG82Y2AOQ","type":"ADD_ALIAS"},"ledgerTimestamp":1604621739791,"uuid":"CpTpb7B1BI42v4QzNOBfPQ","version":"1"}
{"action":{"identity":{"address":"N\u0000sourcecred\u0000core\u0000IDENTITY\u000053rzgGRNmQjVJUB84Ox9Jw\u0000","aliases":[],"id":"53rzgGRNmQjVJUB84Ox9Jw","name":"ioncloud-eth","subtype":"USER"},"type":"CREATE_IDENTITY"},"ledgerTimestamp":1604621739792,"uuid":"vZnohyzfQ18qT2K2OqekfQ","version":"1"}
{"action":{"alias":{"address":"N\u0000sourcecred\u0000discord\u0000MEMBER\u0000user\u0000714949845592440986\u0000","description":"discord/ioncloud.eth#1579"},"identityId":"53rzgGRNmQjVJUB84Ox9Jw","type":"ADD_ALIAS"},"ledgerTimestamp":1604621739792,"uuid":"BDmb1J0TEpgumxG8DFgk7A","version":"1"}
{"action":{"identity":{"address":"N\u0000sourcecred\u0000core\u0000IDENTITY\u0000fGUP1SKU11Bl71Qn3qO78g\u0000","aliases":[],"id":"fGUP1SKU11Bl71Qn3qO78g","name":"cccc","subtype":"USER"},"type":"CREATE_IDENTITY"},"ledgerTimestamp":1604621739792,"uuid":"jxfxYtOvBHYqSWNN29oQmA","version":"1"}
{"action":{"alias":{"address":"N\u0000sourcecred\u0000discord\u0000MEMBER\u0000user\u0000715143737155518465\u0000","description":"discord/cccc#8753"},"identityId":"fGUP1SKU11Bl71Qn3qO78g","type":"ADD_ALIAS"},"ledgerTimestamp":1604621739792,"uuid":"WMldnlWaZwuyMwrIrPVnVQ","version":"1"}
{"action":{"identity":{"address":"N\u0000sourcecred\u0000core\u0000IDENTITY\u0000DntyTZjVTv3FeyBcP39T2g\u0000","aliases":[],"id":"DntyTZjVTv3FeyBcP39T2g","name":"jedrulez2k","subtype":"USER"},"type":"CREATE_IDENTITY"},"ledgerTimestamp":1604621739792,"uuid":"NNvj3mB2gTdd5sWCVQdp5Q","version":"1"}
{"action":{"alias":{"address":"N\u0000sourcecred\u0000discord\u0000MEMBER\u0000user\u0000721075069677338667\u0000","description":"discord/jedrulez2k#9444"},"identityId":"DntyTZjVTv3FeyBcP39T2g","type":"ADD_ALIAS"},"ledgerTimestamp":1604621739792,"uuid":"VlvYWf7a6Bcwh97EmK1zfQ","version":"1"}
{"action":{"identity":{"address":"N\u0000sourcecred\u0000core\u0000IDENTITY\u0000d3SjUyDzND9g3E0yVlFgAg\u0000","aliases":[],"id":"d3SjUyDzND9g3E0yVlFgAg","name":"Darren","subtype":"USER"},"type":"CREATE_IDENTITY"},"ledgerTimestamp":1604621739792,"uuid":"jvaULr85FPmaEo79mWDujw","version":"1"}
{"action":{"alias":{"address":"N\u0000sourcecred\u0000discord\u0000MEMBER\u0000user\u0000724425732604035104\u0000","description":"discord/Darren#1403"},"identityId":"d3SjUyDzND9g3E0yVlFgAg","type":"ADD_ALIAS"},"ledgerTimestamp":1604621739792,"uuid":"ehkDugjSaF6sV2AxUb4c8Q","version":"1"}
{"action":{"identity":{"address":"N\u0000sourcecred\u0000core\u0000IDENTITY\u0000fKGcPtouA69UMWfXAFdGzA\u0000","aliases":[],"id":"fKGcPtouA69UMWfXAFdGzA","name":"Jess-Sloss","subtype":"USER"},"type":"CREATE_IDENTITY"},"ledgerTimestamp":1604621739792,"uuid":"GuvZ6cnTOja3D3epEuQWxg","version":"1"}
{"action":{"alias":{"address":"N\u0000sourcecred\u0000discord\u0000MEMBER\u0000user\u0000730219814462816306\u0000","description":"discord/Jess Sloss#7347"},"identityId":"fKGcPtouA69UMWfXAFdGzA","type":"ADD_ALIAS"},"ledgerTimestamp":1604621739792,"uuid":"o5tv5DEygiwSaf49D9AjqA","version":"1"}
{"action":{"identity":{"address":"N\u0000sourcecred\u0000core\u0000IDENTITY\u0000TMMH2EsjWWtMPbFMYLXH2A\u0000","aliases":[],"id":"TMMH2EsjWWtMPbFMYLXH2A","name":"Alxxxxx","subtype":"USER"},"type":"CREATE_IDENTITY"},"ledgerTimestamp":1604621739792,"uuid":"GbJIMRKTlIRBmDrGF4rByQ","version":"1"}
{"action":{"alias":{"address":"N\u0000sourcecred\u0000discord\u0000MEMBER\u0000user\u0000734095506648596531\u0000","description":"discord/Alxxxxx#3539"},"identityId":"TMMH2EsjWWtMPbFMYLXH2A","type":"ADD_ALIAS"},"ledgerTimestamp":1604621739792,"uuid":"DTqLTpXgpLBbrqPt5kVg0w","version":"1"}
{"action":{"identity":{"address":"N\u0000sourcecred\u0000core\u0000IDENTITY\u0000GfY2un1PVYDG10y7BYOubA\u0000","aliases":[],"id":"GfY2un1PVYDG10y7BYOubA","name":"Ian--Uniswap-","subtype":"USER"},"type":"CREATE_IDENTITY"},"ledgerTimestamp":1604621739792,"uuid":"eYY2flGvClJcdv7sZQQBhw","version":"1"}
{"action":{"alias":{"address":"N\u0000sourcecred\u0000discord\u0000MEMBER\u0000user\u0000736396394763386910\u0000","description":"discord/Ian (Uniswap)#6473"},"identityId":"GfY2un1PVYDG10y7BYOubA","type":"ADD_ALIAS"},"ledgerTimestamp":1604621739792,"uuid":"7WQNYyyF6x4UV05o533VaA","version":"1"}
{"action":{"identity":{"address":"N\u0000sourcecred\u0000core\u0000IDENTITY\u0000wxkRyWWsBvPBmnZApcK0HA\u0000","aliases":[],"id":"wxkRyWWsBvPBmnZApcK0HA","name":"Jams","subtype":"USER"},"type":"CREATE_IDENTITY"},"ledgerTimestamp":1604621739792,"uuid":"lOm5LvfJBPyAYvZhkebt4g","version":"1"}
{"action":{"alias":{"address":"N\u0000sourcecred\u0000discord\u0000MEMBER\u0000user\u0000736709108757168211\u0000","description":"discord/Jams#8593"},"identityId":"wxkRyWWsBvPBmnZApcK0HA","type":"ADD_ALIAS"},"ledgerTimestamp":1604621739792,"uuid":"DxKDIXLIvqrjZF2cm36Oog","version":"1"}
{"action":{"identity":{"address":"N\u0000sourcecred\u0000core\u0000IDENTITY\u0000LsWMX4E40oh5kAqiwrWu1Q\u0000","aliases":[],"id":"LsWMX4E40oh5kAqiwrWu1Q","name":"C--or-Pixellitist","subtype":"USER"},"type":"CREATE_IDENTITY"},"ledgerTimestamp":1604621739792,"uuid":"M1GmLC7p6qANGjH8jhj1vQ","version":"1"}
{"action":{"alias":{"address":"N\u0000sourcecred\u0000discord\u0000MEMBER\u0000user\u0000742127445297201152\u0000","description":"discord/C. or Pixellitist#9970"},"identityId":"LsWMX4E40oh5kAqiwrWu1Q","type":"ADD_ALIAS"},"ledgerTimestamp":1604621739792,"uuid":"ioLEjik4L6JrQQyBI1RwEw","version":"1"}
{"action":{"identity":{"address":"N\u0000sourcecred\u0000core\u0000IDENTITY\u0000d5vsw5IBpc8R9rwUqgJEww\u0000","aliases":[],"id":"d5vsw5IBpc8R9rwUqgJEww","name":"jjjjjj","subtype":"USER"},"type":"CREATE_IDENTITY"},"ledgerTimestamp":1604621739793,"uuid":"bLN248vDSDDu1KO4EBCNXQ","version":"1"}
{"action":{"alias":{"address":"N\u0000sourcecred\u0000discord\u0000MEMBER\u0000user\u0000742626456449843301\u0000","description":"discord/jjjjjj#8061"},"identityId":"d5vsw5IBpc8R9rwUqgJEww","type":"ADD_ALIAS"},"ledgerTimestamp":1604621739793,"uuid":"XXYJ8xkgix1z5qXSVijr4A","version":"1"}
{"action":{"identity":{"address":"N\u0000sourcecred\u0000core\u0000IDENTITY\u0000OKpR8qG7QYlBGas8LpkXDQ\u0000","aliases":[],"id":"OKpR8qG7QYlBGas8LpkXDQ","name":"abcxd","subtype":"USER"},"type":"CREATE_IDENTITY"},"ledgerTimestamp":1604621739793,"uuid":"O8Bkh2e933Ri1S7BBlOyjQ","version":"1"}
{"action":{"alias":{"address":"N\u0000sourcecred\u0000discord\u0000MEMBER\u0000user\u0000744236017011130518\u0000","description":"discord/abcxd#9480"},"identityId":"OKpR8qG7QYlBGas8LpkXDQ","type":"ADD_ALIAS"},"ledgerTimestamp":1604621739793,"uuid":"a4rTqfplTdPdLJktwFkvdQ","version":"1"}
{"action":{"identity":{"address":"N\u0000sourcecred\u0000core\u0000IDENTITY\u0000kXSy9MtJ5x9F6QXLX5j4PQ\u0000","aliases":[],"id":"kXSy9MtJ5x9F6QXLX5j4PQ","name":"stopitsria","subtype":"USER"},"type":"CREATE_IDENTITY"},"ledgerTimestamp":1604621739793,"uuid":"mhKlPjrZmCyjGPQ78gImow","version":"1"}
{"action":{"alias":{"address":"N\u0000sourcecred\u0000discord\u0000MEMBER\u0000user\u0000745731184679583747\u0000","description":"discord/stopitsria#1152"},"identityId":"kXSy9MtJ5x9F6QXLX5j4PQ","type":"ADD_ALIAS"},"ledgerTimestamp":1604621739793,"uuid":"D3oW97bxv6c4i804fB05bg","version":"1"}
{"action":{"identity":{"address":"N\u0000sourcecred\u0000core\u0000IDENTITY\u0000B6qQh98jm0nHNlW50WguLw\u0000","aliases":[],"id":"B6qQh98jm0nHNlW50WguLw","name":"Tommy---UMA","subtype":"USER"},"type":"CREATE_IDENTITY"},"ledgerTimestamp":1604621739793,"uuid":"AYIMAjSdI5JTZz2t7s9dNg","version":"1"}
{"action":{"alias":{"address":"N\u0000sourcecred\u0000discord\u0000MEMBER\u0000user\u0000751604392146239560\u0000","description":"discord/Tommy | UMA#4399"},"identityId":"B6qQh98jm0nHNlW50WguLw","type":"ADD_ALIAS"},"ledgerTimestamp":1604621739793,"uuid":"RTa6mlhwLLgVLm5vTJlB2A","version":"1"}
{"action":{"identity":{"address":"N\u0000sourcecred\u0000core\u0000IDENTITY\u0000Tg5ujKqFLS5x8eXgYEEpqw\u0000","aliases":[],"id":"Tg5ujKqFLS5x8eXgYEEpqw","name":"SC-JammSess","subtype":"BOT"},"type":"CREATE_IDENTITY"},"ledgerTimestamp":1604621739793,"uuid":"wWnzmjPyXgvAU9cNu4XB3A","version":"1"}
{"action":{"alias":{"address":"N\u0000sourcecred\u0000discord\u0000MEMBER\u0000bot\u0000755091638715416672\u0000","description":"discord/SC-JammSess#4168"},"identityId":"Tg5ujKqFLS5x8eXgYEEpqw","type":"ADD_ALIAS"},"ledgerTimestamp":1604621739793,"uuid":"EzGwZKQ5nVTJeJhlGfqK2Q","version":"1"}
{"action":{"identity":{"address":"N\u0000sourcecred\u0000core\u0000IDENTITY\u0000CvWg91K2vGFDhW7jVs4vrg\u0000","aliases":[],"id":"CvWg91K2vGFDhW7jVs4vrg","name":"bashalex","subtype":"USER"},"type":"CREATE_IDENTITY"},"ledgerTimestamp":1604621739793,"uuid":"BAF4UYMUWGFxGfAzOAGing","version":"1"}
{"action":{"alias":{"address":"N\u0000sourcecred\u0000discord\u0000MEMBER\u0000user\u0000755476401603346663\u0000","description":"discord/bashalex#8527"},"identityId":"CvWg91K2vGFDhW7jVs4vrg","type":"ADD_ALIAS"},"ledgerTimestamp":1604621739793,"uuid":"a0DKT6keo9NX0HogmTzqHA","version":"1"}
{"action":{"identity":{"address":"N\u0000sourcecred\u0000core\u0000IDENTITY\u0000XdMAiW0DheukQt1m1pW4cw\u0000","aliases":[],"id":"XdMAiW0DheukQt1m1pW4cw","name":"toshi","subtype":"USER"},"type":"CREATE_IDENTITY"},"ledgerTimestamp":1604621739794,"uuid":"2djYp5jRvjwlXpD90VDz4g","version":"1"}
{"action":{"alias":{"address":"N\u0000sourcecred\u0000discord\u0000MEMBER\u0000user\u0000761023912631992331\u0000","description":"discord/toshi#3611"},"identityId":"XdMAiW0DheukQt1m1pW4cw","type":"ADD_ALIAS"},"ledgerTimestamp":1604621739794,"uuid":"ymKg36fqnlg4mqEbgNkwTA","version":"1"}
{"action":{"identity":{"address":"N\u0000sourcecred\u0000core\u0000IDENTITY\u0000UWryWJ4jWcAAV2VCBoQZvA\u0000","aliases":[],"id":"UWryWJ4jWcAAV2VCBoQZvA","name":"chriscollins","subtype":"USER"},"type":"CREATE_IDENTITY"},"ledgerTimestamp":1604621739794,"uuid":"WbxsdEkrpV572GDDwHeYtw","version":"1"}
{"action":{"alias":{"address":"N\u0000sourcecred\u0000discord\u0000MEMBER\u0000user\u0000761285444905205791\u0000","description":"discord/chriscollins#7081"},"identityId":"UWryWJ4jWcAAV2VCBoQZvA","type":"ADD_ALIAS"},"ledgerTimestamp":1604621739794,"uuid":"oPltx80qob0f7Mdj6Ujc7g","version":"1"}
{"action":{"identity":{"address":"N\u0000sourcecred\u0000core\u0000IDENTITY\u0000NBjmsOuZw9PPGFBRRDMLZg\u0000","aliases":[],"id":"NBjmsOuZw9PPGFBRRDMLZg","name":"Wilma-Lane","subtype":"USER"},"type":"CREATE_IDENTITY"},"ledgerTimestamp":1604621739794,"uuid":"uZMgBzTZWUoZBwX8d7tO5g","version":"1"}
{"action":{"alias":{"address":"N\u0000sourcecred\u0000discord\u0000MEMBER\u0000user\u0000763042841680281651\u0000","description":"discord/Wilma Lane#8805"},"identityId":"NBjmsOuZw9PPGFBRRDMLZg","type":"ADD_ALIAS"},"ledgerTimestamp":1604621739794,"uuid":"Vnd1aPDm8Ezdn8KsYPFBww","version":"1"}
{"action":{"identity":{"address":"N\u0000sourcecred\u0000core\u0000IDENTITY\u0000MGrdgZRarLVZtVQxfbi5Yg\u0000","aliases":[],"id":"MGrdgZRarLVZtVQxfbi5Yg","name":"temmanuel","subtype":"USER"},"type":"CREATE_IDENTITY"},"ledgerTimestamp":1604621739794,"uuid":"ovLfqCy1F04BEl6n0sjxRA","version":"1"}
{"action":{"alias":{"address":"N\u0000sourcecred\u0000discord\u0000MEMBER\u0000user\u0000763888621203488779\u0000","description":"discord/temmanuel#8040"},"identityId":"MGrdgZRarLVZtVQxfbi5Yg","type":"ADD_ALIAS"},"ledgerTimestamp":1604621739794,"uuid":"J5Q8HLhoG7lEKMyenpFw8g","version":"1"}
{"action":{"identity":{"address":"N\u0000sourcecred\u0000core\u0000IDENTITY\u0000r1GmJG36Qsq5ykPD9ZsxMg\u0000","aliases":[],"id":"r1GmJG36Qsq5ykPD9ZsxMg","name":"conradcarr8","subtype":"USER"},"type":"CREATE_IDENTITY"},"ledgerTimestamp":1604621739794,"uuid":"OrEMtLlUmSoYn4QtxWLPYQ","version":"1"}
{"action":{"alias":{"address":"N\u0000sourcecred\u0000discord\u0000MEMBER\u0000user\u0000764972863756959764\u0000","description":"discord/conradcarr8#0109"},"identityId":"r1GmJG36Qsq5ykPD9ZsxMg","type":"ADD_ALIAS"},"ledgerTimestamp":1604621739794,"uuid":"aoIMnXLdddU05pWpVD7GHg","version":"1"}
{"action":{"identity":{"address":"N\u0000sourcecred\u0000core\u0000IDENTITY\u0000qUgzqR4Du47YXIaEKT1Rjg\u0000","aliases":[],"id":"qUgzqR4Du47YXIaEKT1Rjg","name":"Jamm-SessCred","subtype":"BOT"},"type":"CREATE_IDENTITY"},"ledgerTimestamp":1604621739794,"uuid":"KJjROjSXllAN3qn7Bw0NuA","version":"1"}
{"action":{"alias":{"address":"N\u0000sourcecred\u0000discord\u0000MEMBER\u0000bot\u0000767776949686632488\u0000","description":"discord/Jamm SessCred#2134"},"identityId":"qUgzqR4Du47YXIaEKT1Rjg","type":"ADD_ALIAS"},"ledgerTimestamp":1604621739794,"uuid":"kRAEnzlEcRqTwxIBhe1Dow","version":"1"}
{"action":{"identity":{"address":"N\u0000sourcecred\u0000core\u0000IDENTITY\u00004bWPPBx5IZCqbgligfNzgQ\u0000","aliases":[],"id":"4bWPPBx5IZCqbgligfNzgQ","name":"Jason","subtype":"USER"},"type":"CREATE_IDENTITY"},"ledgerTimestamp":1604621739794,"uuid":"AIYLXOolQYT6fRdLyELqVQ","version":"1"}
{"action":{"alias":{"address":"N\u0000sourcecred\u0000discord\u0000MEMBER\u0000user\u000096284499003834368\u0000","description":"discord/Jason#7132"},"identityId":"4bWPPBx5IZCqbgligfNzgQ","type":"ADD_ALIAS"},"ledgerTimestamp":1604621739795,"uuid":"hRuAGKvKdZaMMGie16NzTg","version":"1"}
{"action":{"identity":{"address":"N\u0000sourcecred\u0000core\u0000IDENTITY\u0000ncRnV0pj5w8zoz4AuwDdFg\u0000","aliases":[],"id":"ncRnV0pj5w8zoz4AuwDdFg","name":"Michael-A----JST----marnold-mch","subtype":"USER"},"type":"CREATE_IDENTITY"},"ledgerTimestamp":1604621739795,"uuid":"cbPDuV9VZkBHm08fZ1h8SA","version":"1"}
{"action":{"alias":{"address":"N\u0000sourcecred\u0000discord\u0000MEMBER\u0000user\u0000166891624331345920\u0000","description":"discord/Michael A. | JST | @marnold_mch#6791"},"identityId":"ncRnV0pj5w8zoz4AuwDdFg","type":"ADD_ALIAS"},"ledgerTimestamp":1604621739795,"uuid":"ZczMqgV5gTa1SNbF2925yQ","version":"1"}
{"action":{"identity":{"address":"N\u0000sourcecred\u0000core\u0000IDENTITY\u0000rPA7I3s5JGDsEYIp1lTvKA\u0000","aliases":[],"id":"rPA7I3s5JGDsEYIp1lTvKA","name":"DragoNate","subtype":"USER"},"type":"CREATE_IDENTITY"},"ledgerTimestamp":1604621739795,"uuid":"jLdz13MInLrOoBh3D1vckA","version":"1"}
{"action":{"alias":{"address":"N\u0000sourcecred\u0000discord\u0000MEMBER\u0000user\u0000272179651437395969\u0000","description":"discord/DragoNate#8523"},"identityId":"rPA7I3s5JGDsEYIp1lTvKA","type":"ADD_ALIAS"},"ledgerTimestamp":1604621739795,"uuid":"rXL3yMQLRu55lsxM1nj4Fg","version":"1"}
{"action":{"identity":{"address":"N\u0000sourcecred\u0000core\u0000IDENTITY\u0000uG6wSJc6BAvgEIGU0c0wpg\u0000","aliases":[],"id":"uG6wSJc6BAvgEIGU0c0wpg","name":"shen","subtype":"USER"},"type":"CREATE_IDENTITY"},"ledgerTimestamp":1604621739795,"uuid":"2OoH06RNe9AFkXLK41tMmA","version":"1"}
{"action":{"alias":{"address":"N\u0000sourcecred\u0000discord\u0000MEMBER\u0000user\u0000319993153425768448\u0000","description":"discord/shen#7437"},"identityId":"uG6wSJc6BAvgEIGU0c0wpg","type":"ADD_ALIAS"},"ledgerTimestamp":1604621739795,"uuid":"tbeTKQpby3hNTmAF4T0VXg","version":"1"}
{"action":{"identity":{"address":"N\u0000sourcecred\u0000core\u0000IDENTITY\u0000bVUBsBgFzjGb8uvHAQ2jNg\u0000","aliases":[],"id":"bVUBsBgFzjGb8uvHAQ2jNg","name":"MisterGore","subtype":"USER"},"type":"CREATE_IDENTITY"},"ledgerTimestamp":1604621739795,"uuid":"JmxjOnXv5oLWfJvWpcG0SQ","version":"1"}
{"action":{"alias":{"address":"N\u0000sourcecred\u0000discord\u0000MEMBER\u0000user\u0000334148767412387841\u0000","description":"discord/MisterGore#9782"},"identityId":"bVUBsBgFzjGb8uvHAQ2jNg","type":"ADD_ALIAS"},"ledgerTimestamp":1604621739795,"uuid":"dS4mSEU5qC8mUdUoK5nT4A","version":"1"}
{"action":{"identity":{"address":"N\u0000sourcecred\u0000core\u0000IDENTITY\u0000mrKZxfnkBbwQqajNsEM2JA\u0000","aliases":[],"id":"mrKZxfnkBbwQqajNsEM2JA","name":"rewired","subtype":"USER"},"type":"CREATE_IDENTITY"},"ledgerTimestamp":1604621739795,"uuid":"2SWcLxnKzYRvyMoE3NUG4w","version":"1"}
{"action":{"alias":{"address":"N\u0000sourcecred\u0000discord\u0000MEMBER\u0000user\u0000346793842969935873\u0000","description":"discord/rewired#0397"},"identityId":"mrKZxfnkBbwQqajNsEM2JA","type":"ADD_ALIAS"},"ledgerTimestamp":1604621739795,"uuid":"xxn97EtAv2WTXyOEzPKEzA","version":"1"}
{"action":{"identity":{"address":"N\u0000sourcecred\u0000core\u0000IDENTITY\u0000CdqE55D9juAiOEXxYxbJ6A\u0000","aliases":[],"id":"CdqE55D9juAiOEXxYxbJ6A","name":"Patrick---EST----pi0neerpat","subtype":"USER"},"type":"CREATE_IDENTITY"},"ledgerTimestamp":1604621739795,"uuid":"AXvrbGnjqlN0Z6aOrS0jMA","version":"1"}
{"action":{"alias":{"address":"N\u0000sourcecred\u0000discord\u0000MEMBER\u0000user\u0000381135787330109441\u0000","description":"discord/Patrick | EST | @pi0neerpat#4947"},"identityId":"CdqE55D9juAiOEXxYxbJ6A","type":"ADD_ALIAS"},"ledgerTimestamp":1604621739795,"uuid":"9C4jHw5FdJPCgPBgObVmSg","version":"1"}
{"action":{"identity":{"address":"N\u0000sourcecred\u0000core\u0000IDENTITY\u0000NAVmCNR5DGmpWnoBTWY6ng\u0000","aliases":[],"id":"NAVmCNR5DGmpWnoBTWY6ng","name":"Ben-Sparango","subtype":"USER"},"type":"CREATE_IDENTITY"},"ledgerTimestamp":1604621739795,"uuid":"cM9PHVTWVoV1BrEeZ16abw","version":"1"}
{"action":{"alias":{"address":"N\u0000sourcecred\u0000discord\u0000MEMBER\u0000user\u0000386641762329952261\u0000","description":"discord/Ben Sparango#2740"},"identityId":"NAVmCNR5DGmpWnoBTWY6ng","type":"ADD_ALIAS"},"ledgerTimestamp":1604621739795,"uuid":"vs3AEqU8vhmtPQqah504sg","version":"1"}
{"action":{"identity":{"address":"N\u0000sourcecred\u0000core\u0000IDENTITY\u0000j23Py3ntERAiGwkendSnxA\u0000","aliases":[],"id":"j23Py3ntERAiGwkendSnxA","name":"magneter01","subtype":"USER"},"type":"CREATE_IDENTITY"},"ledgerTimestamp":1604621739795,"uuid":"UWJYrz1305bUy9yv2kc5UQ","version":"1"}
{"action":{"alias":{"address":"N\u0000sourcecred\u0000discord\u0000MEMBER\u0000user\u0000394397314258698243\u0000","description":"discord/magneter01#0654"},"identityId":"j23Py3ntERAiGwkendSnxA","type":"ADD_ALIAS"},"ledgerTimestamp":1604621739795,"uuid":"KSbfwYw8Oy5z78evbfAToA","version":"1"}
{"action":{"identity":{"address":"N\u0000sourcecred\u0000core\u0000IDENTITY\u00006MV4BAhaZYq7tL386yeDMQ\u0000","aliases":[],"id":"6MV4BAhaZYq7tL386yeDMQ","name":"AdamStark","subtype":"USER"},"type":"CREATE_IDENTITY"},"ledgerTimestamp":1604621739795,"uuid":"SjBselTEF3WVQXObUj6xaA","version":"1"}
{"action":{"alias":{"address":"N\u0000sourcecred\u0000discord\u0000MEMBER\u0000user\u0000398861960491565057\u0000","description":"discord/AdamStark#4164"},"identityId":"6MV4BAhaZYq7tL386yeDMQ","type":"ADD_ALIAS"},"ledgerTimestamp":1604621739795,"uuid":"A7GoOHLINFjpqkmk3nOZJQ","version":"1"}
{"action":{"identity":{"address":"N\u0000sourcecred\u0000core\u0000IDENTITY\u0000MTXfrR6rKkw12KdZnmRWAg\u0000","aliases":[],"id":"MTXfrR6rKkw12KdZnmRWAg","name":"arsel","subtype":"USER"},"type":"CREATE_IDENTITY"},"ledgerTimestamp":1604621739796,"uuid":"sgZL0iXiJXbjf0QWs6DAOQ","version":"1"}
{"action":{"alias":{"address":"N\u0000sourcecred\u0000discord\u0000MEMBER\u0000user\u0000479098593178025994\u0000","description":"discord/arsel#5917"},"identityId":"MTXfrR6rKkw12KdZnmRWAg","type":"ADD_ALIAS"},"ledgerTimestamp":1604621739796,"uuid":"PIMMMm1cm7g9VRhqSNf8jw","version":"1"}
{"action":{"identity":{"address":"N\u0000sourcecred\u0000core\u0000IDENTITY\u0000prjV2xGzaYXVLJFzvAru7w\u0000","aliases":[],"id":"prjV2xGzaYXVLJFzvAru7w","name":"kai","subtype":"USER"},"type":"CREATE_IDENTITY"},"ledgerTimestamp":1604621739796,"uuid":"olTwuBe5m6QjP4zv1i1qbA","version":"1"}
{"action":{"alias":{"address":"N\u0000sourcecred\u0000discord\u0000MEMBER\u0000user\u0000500576676154048526\u0000","description":"discord/kai#4657"},"identityId":"prjV2xGzaYXVLJFzvAru7w","type":"ADD_ALIAS"},"ledgerTimestamp":1604621739796,"uuid":"RiDhr57iRqB8BxhBBVXevw","version":"1"}
{"action":{"identity":{"address":"N\u0000sourcecred\u0000core\u0000IDENTITY\u0000PDN2tvOdYArUYRcodfprJA\u0000","aliases":[],"id":"PDN2tvOdYArUYRcodfprJA","name":"Powers","subtype":"USER"},"type":"CREATE_IDENTITY"},"ledgerTimestamp":1604621739796,"uuid":"7gQ5c4dZy0nx0IgHA7H67Q","version":"1"}
{"action":{"alias":{"address":"N\u0000sourcecred\u0000discord\u0000MEMBER\u0000user\u0000542389331461931034\u0000","description":"discord/Powers#2897"},"identityId":"PDN2tvOdYArUYRcodfprJA","type":"ADD_ALIAS"},"ledgerTimestamp":1604621739796,"uuid":"ImekZetKiAvu15LRDFAhEw","version":"1"}
{"action":{"identity":{"address":"N\u0000sourcecred\u0000core\u0000IDENTITY\u00006BmNvlWlhrbFOww4YcBxeg\u0000","aliases":[],"id":"6BmNvlWlhrbFOww4YcBxeg","name":"NFTMerchant","subtype":"USER"},"type":"CREATE_IDENTITY"},"ledgerTimestamp":1604621739796,"uuid":"tAJrRS2BRy6hkBdbTrd0qg","version":"1"}
{"action":{"alias":{"address":"N\u0000sourcecred\u0000discord\u0000MEMBER\u0000user\u0000555843972459921411\u0000","description":"discord/NFTMerchant#2828"},"identityId":"6BmNvlWlhrbFOww4YcBxeg","type":"ADD_ALIAS"},"ledgerTimestamp":1604621739796,"uuid":"1rGvooIozsryuewo4nCntA","version":"1"}
{"action":{"identity":{"address":"N\u0000sourcecred\u0000core\u0000IDENTITY\u0000OpDmrS04ARJezbP7aEa6Ug\u0000","aliases":[],"id":"OpDmrS04ARJezbP7aEa6Ug","name":"WilliamM","subtype":"USER"},"type":"CREATE_IDENTITY"},"ledgerTimestamp":1604621739796,"uuid":"tQNZc3xkoj9gDkUYUQOewQ","version":"1"}
{"action":{"alias":{"address":"N\u0000sourcecred\u0000discord\u0000MEMBER\u0000user\u0000581246712299913231\u0000","description":"discord/WilliamM#0127"},"identityId":"OpDmrS04ARJezbP7aEa6Ug","type":"ADD_ALIAS"},"ledgerTimestamp":1604621739796,"uuid":"TOyM6Vi8B9fJyoLU0En67Q","version":"1"}
{"action":{"identity":{"address":"N\u0000sourcecred\u0000core\u0000IDENTITY\u0000JlPkTgtGWvurnhkf8up7KQ\u0000","aliases":[],"id":"JlPkTgtGWvurnhkf8up7KQ","name":"hexa-d","subtype":"USER"},"type":"CREATE_IDENTITY"},"ledgerTimestamp":1604621739797,"uuid":"1fbsJtjzdhje7mQ38hkOBQ","version":"1"}
{"action":{"alias":{"address":"N\u0000sourcecred\u0000discord\u0000MEMBER\u0000user\u0000591366184775974914\u0000","description":"discord/hexa_d#6400"},"identityId":"JlPkTgtGWvurnhkf8up7KQ","type":"ADD_ALIAS"},"ledgerTimestamp":1604621739797,"uuid":"5dl6qcLOYGUvoYrRcgigOw","version":"1"}
{"action":{"identity":{"address":"N\u0000sourcecred\u0000core\u0000IDENTITY\u0000qgcPLM5OVJk24hyt57LT3g\u0000","aliases":[],"id":"qgcPLM5OVJk24hyt57LT3g","name":"wslyvh","subtype":"USER"},"type":"CREATE_IDENTITY"},"ledgerTimestamp":1604621739797,"uuid":"NWtPEqbfBVlmkbmeolalYg","version":"1"}
{"action":{"alias":{"address":"N\u0000sourcecred\u0000discord\u0000MEMBER\u0000user\u0000615886828582469635\u0000","description":"discord/wslyvh#1059"},"identityId":"qgcPLM5OVJk24hyt57LT3g","type":"ADD_ALIAS"},"ledgerTimestamp":1604621739797,"uuid":"nfoYLnM5kX8qURC9YtP6dg","version":"1"}
{"action":{"identity":{"address":"N\u0000sourcecred\u0000core\u0000IDENTITY\u00005N3uNuZ3XMVZW6Ke8cVNCw\u0000","aliases":[],"id":"5N3uNuZ3XMVZW6Ke8cVNCw","name":"michael01","subtype":"USER"},"type":"CREATE_IDENTITY"},"ledgerTimestamp":1604621739797,"uuid":"MxX1X9cjDSNlLVFe9gZbaA","version":"1"}
{"action":{"alias":{"address":"N\u0000sourcecred\u0000discord\u0000MEMBER\u0000user\u0000630999030897573900\u0000","description":"discord/michael01#6441"},"identityId":"5N3uNuZ3XMVZW6Ke8cVNCw","type":"ADD_ALIAS"},"ledgerTimestamp":1604621739797,"uuid":"gXxEPZ5yWTaUApCQ9TZuvg","version":"1"}
{"action":{"identity":{"address":"N\u0000sourcecred\u0000core\u0000IDENTITY\u0000MYQMMY42zI2ZlllyWnWMsA\u0000","aliases":[],"id":"MYQMMY42zI2ZlllyWnWMsA","name":"Aidan---LTF","subtype":"USER"},"type":"CREATE_IDENTITY"},"ledgerTimestamp":1604621739797,"uuid":"GU7omvzT46x8Q7zZmjJ72Q","version":"1"}
{"action":{"alias":{"address":"N\u0000sourcecred\u0000discord\u0000MEMBER\u0000user\u0000686755249138302977\u0000","description":"discord/Aidan | LTF#1666"},"identityId":"MYQMMY42zI2ZlllyWnWMsA","type":"ADD_ALIAS"},"ledgerTimestamp":1604621739797,"uuid":"DUYYiELY8s5gV47SjAf9lw","version":"1"}
{"action":{"identity":{"address":"N\u0000sourcecred\u0000core\u0000IDENTITY\u0000toCDRhRMXy9sxXqNFMzqqA\u0000","aliases":[],"id":"toCDRhRMXy9sxXqNFMzqqA","name":"Lindy","subtype":"USER"},"type":"CREATE_IDENTITY"},"ledgerTimestamp":1604621739797,"uuid":"7Jeru9jmZMm5sR0DcY5Vow","version":"1"}
{"action":{"alias":{"address":"N\u0000sourcecred\u0000discord\u0000MEMBER\u0000user\u0000724604731011366913\u0000","description":"discord/Lindy#0442"},"identityId":"toCDRhRMXy9sxXqNFMzqqA","type":"ADD_ALIAS"},"ledgerTimestamp":1604621739797,"uuid":"N9WoOwg0Td0rpSpyzPZX8g","version":"1"}
{"action":{"identity":{"address":"N\u0000sourcecred\u0000core\u0000IDENTITY\u0000mpRLGi3qpUWcqEYRtreGgw\u0000","aliases":[],"id":"mpRLGi3qpUWcqEYRtreGgw","name":"SourceCred","subtype":"PROJECT"},"type":"CREATE_IDENTITY"},"ledgerTimestamp":1604621740498,"uuid":"hLAt8qkf7UGTMawRKXbJ0Q","version":"1"}
{"action":{"identityId":"mpRLGi3qpUWcqEYRtreGgw","type":"TOGGLE_ACTIVATION"},"ledgerTimestamp":1604621740498,"uuid":"Owwnx3ecOwXAZSlWGLSAfA","version":"1"}
